Workbook
Name pricetable: #REF!
Name pricetable: #REF!
Name pricetable: #REF!
Name pricetable: #REF!
Name pricetable: #REF!

Sheet shipper master
A1: 1 | B1: S/CODE | C1: SHIPPER NAME
A2: =A1+1 -> 2 | B2: SHIPPER | C2: SHUNYA CO., LTD.
A3: =A2+1 -> 3 | B3: SHIPPER ADDRESS 1 | C3: KENSHIN BLDG., 1F, 1-22-10 DOUGENZAKA,
A4: =A3+1 -> 4 | B4: SHIPPER ADDRESS 2 | C4: SHIBUYA-KU 150-0043
A5: =A4+1 -> 5 | B5: SHIPPER ADDRESS 3 | C5: TEL : +81(0)3-5459-1177
A6: =A5+1 -> 6 | B6: TEL
A7: =A6+1 -> 7 | B7: FAX
A8: =A7+1 -> 8 | B8: ATTN OR VAT NO.
A9: =A8+1 -> 9 | B9: BUYER | C9: VIVAN GARMENTS VIET NAM COMPANY LIMITED
A10: =A9+1 -> 10 | B10: BUYER ADDRESS1 | C10: No.10 , D17 Street , Sai Gon South Residential Area
A11: =A10+1 -> 11 | B11: BUYER ADDRESS2 | C11: Hamlet 3 , Long Hau Commune , Can Giuoc District,
A12: =A11+1 -> 12 | B12: BUYER ADDRESS3 | C12: Long An Province , VietNam
A13: =A12+1 -> 13 | B13: TEL/FAX | C13: TEL : ( 084 ) 097 22 00 798 ATTN : MR. TUAN
A14: =A13+1 -> 14 | B14: ATTN
A15: =A14+1 -> 15 | B15: CONSIGNEE : | C15: - SAME AS BUYER -
A16: =A15+1 -> 16 | B16: CONSIGNEE ADDRESS1
A17: =A16+1 -> 17 | B17: CONSIGNEE ADDRESS2
A18: =A17+1 -> 18 | B18: CONSIGNEE ADDRESS3
A19: =A18+1 -> 19 | B19: TEL
A20: =A19+1 -> 20 | B20: FAX
A21: =A20+1 -> 21 | B21: ATTN | C21: NO COMMERCIAL
A22: =A21+1 -> 22 | B22: PAYMENT 1
A23: =A22+1 -> 23 | B23: PAYMENT 2
A24: =A23+1 -> 24 | B24: SHIPPER PER | C24: AIRCRAFT
A25: =A24+1 -> 25 | B25: INVOICE DATE | C25: NOVEMBER,27 2023
A26: =A25+1 -> 26 | B26: INVOICE NO. | C26: SY-5300419-VT-DD-01
A27: =A26+1 -> 27 | B27: CONTRACT NO. | C27: =C26 -> SY-5300419-VT-DD-01
A28: =A27+1 -> 28 | B28: CONTRACT DATE
A29: =A28+1 -> 29 | B29: ORDER DATE
A30: =A29+1 -> 30 | B30: ORDER NO.
A31: =A30+1 -> 31 | B31: L/C DATE
A32: =A31+1 -> 32 | B32: FROM | C32: TOKYO, JAPAN
A33: =A32+1 -> 33 | B33: TO | C33: HOCHIMINH-CITY, VIETNAM
A34: =A33+1 -> 34 | B34: VIA
A35: =A34+1 -> 35 | B35: SHIPPING TERMS | C35: F.O.B. TOKYO IN YEN
A36: =A35+1 -> 36 | B36: TITTLE 1 | C36: FABRIC & PARTS FOR WEAR & SAMPLE CLOTHES
A37: =A36+1 -> 37 | B37: TITTLE 2
A38: =A37+1 -> 38 | B38: ATTACHE | C38: - DETAILS AS PER ATTACHED SHEET -
A39: =A38+1 -> 39 | B39: C/NO.
A40: =A39+1 -> 40 | B40: STYLE NO.
A41: =A40+1 -> 41 | B41: DESCRIPTION
A42: =A41+1 -> 42 | B42: Q'TY CODE
A43: =A42+1 -> 43 | B43: QUANTITY | C43: 1267.1M 1304PCS. 27SETS.
A44: =A43+1 -> 44 | B44: UNIT PRICE
A45: =A44+1 -> 45 | B45: AMOUNT | C45: =invoice!L31 -> 1909105
A46: =A45+1 -> 46 | B46: DISCOUNT
A47: =A46+1 -> 47 | B47: DISCOUNT
A48: =A47+1 -> 48 | B48: SHIPPING TERMS | C48: F.O.B. TOKYO IN YEN
A49: =A48+1 -> 49 | B49: CASE MARK1 | C49: =C27 -> SY-5300419-VT-DD-01
A50: =A49+1 -> 50 | B50: CASE MARK2 | C50: VIVAN GARMENTS VIET NAM COMPANY LIMITED
A51: =A50+1 -> 51 | B51: CASE MARK3 | C51: No.10 , D17 Street , Sai Gon South Residential Area
A52: =A51+1 -> 52 | B52: CASE MARK4 | C52: Hamlet 3 , Long Hau Commune , Can Giuoc District,
A53: =A52+1 -> 53 | B53: CASE MARK5 | C53: Long An Province , VietNam
A54: =A53+1 -> 54 | B54: CASE MARK6 | C54: TEL : : ( 084 ) 097 22 00 798 ATTN : MR. TUAN
A55: =A54+1 -> 55 | B55: TOTAL | C55: 60PACKAGES
A56: =A55+1 -> 56 | B56: MANUFACTURED BY
A57: =A56+1 -> 57
A58: =A57+1 -> 58
A59: =A58+1 -> 59
A60: =A59+1 -> 60 | B60: ORIGIN | C60: COUNTRY OF ORIGIN : JAPAN
A61: =A60+1 -> 61 | B61: OUR BANK
A62: =A61+1 -> 62
A63: =A62+1 -> 63 | B63: 持ち帰り条件 | C63: " THESE GOODS WILL BE RETURN TO JAPAN
A64: =A63+1 -> 64 | C64: AFTER MANUFACTURED AT VIET NAM "
A65: =A64+1 -> 65
A66: =A65+1 -> 66
A67: =A66+1 -> 67 | B67: ETD TYO
A68: =A67+1 -> 68 | B68: DELIVERY SCHEDULES | C68: END OF JUNE - BEG., OF ＭＡＲ, 2018
A69: =A68+1 -> 69 | B69: INSURANCE | C69: COVERED BY SHIPPER
A70: =A69+1 -> 70 | B70: REMARK 1
A71: =A70+1 -> 71
A72: =A71+1 -> 72
A73: =A72+1 -> 73
A74: =A73+1 -> 74
A75: =A74+1 -> 75 | B75: AIR FREIGHT | C75: PREPAID
A76: =A75+1 -> 76 | B76: YOUR (OUR) FORWARDER
A77: =A76+1 -> 77
A78: =A77+1 -> 78 | B78: CUSTOMS AGENT | C78: MEITETSU WORLD TRANSPORT (MR. NAMIKI)
A79: =A78+1 -> 79 | B79: FORWARDER | C79: MEITETSU WORLD TRANSPORT (MR. NAMIKI)
A80: =A79+1 -> 80
A81: =A80+1 -> 81 | B81: C/O ISSUED DATE | C81: NOV,27, 2023
A82: =A81+1 -> 82
A83: =A82+1 -> 83 | B83: COUNTRY | C83: VIETNAM
A84: =A83+1 -> 84
A85: =A84+1 -> 85
A86: =A85+1 -> 86

Sheet invoice
A1: INVOICE
A2: ='shipper master'!C2 -> SHUNYA CO., LTD.
A3: ='shipper master'!C3 -> KENSHIN BLDG., 1F, 1-22-10 DOUGENZAKA,
A4: ='shipper master'!C4 -> SHIBUYA-KU 150-0043 | K4: ='shipper master'!C6 -> 0
A5: ='shipper master'!C5 -> TEL : +81(0)3-5459-1177 | K5: ='shipper master'!C7 -> 0
A6: IMPORTER | E6: INVOICE NO. | K6: CASE MARK
A7: ='shipper master'!C9 -> VIVAN GARMENTS VIET NAM COMPANY LIMITED | E7: ='shipper master'!C26 -> SY-5300419-VT-DD-01
A8: ='shipper master'!C10 -> No.10 , D17 Street , Sai Gon South Residential Area | E8: INVOICE DATE | K8: ='shipper master'!C49 -> SY-5300419-VT-DD-01
A9: ='shipper master'!C11 -> Hamlet 3 , Long Hau Commune , Can Giuoc District, | E9: ='shipper master'!C25 -> NOVEMBER,27 2023 | K9: ='[1]shipper master'!C50 -> VIVAN GARMENTS VIET NAM
A10: ='shipper master'!C12 -> Long An Province , VietNam | E10: CONTRACT NO. | K10: ='[1]shipper master'!C51 -> COMPANY LIMITED
A11: ='shipper master'!C13 -> TEL : ( 084 ) 097 22 00 798 ATTN : MR. TUAN | E11: ='shipper master'!C27 -> SY-5300419-VT-DD-01 | K11: ='[1]shipper master'!C52 -> HOCHIMINH-CITY, VIETNAM
A12: CONSIGNEE | E12: ORDER NO. | K12: C/NO. 1-60
A13: ='shipper master'!C15 -> - SAME AS BUYER - | E13: ='shipper master'!C30 -> 0 | K13: MADE IN JAPAN
A14: ='shipper master'!C16 -> 0 | E14: ORDER DATE
A15: ='shipper master'!C17 -> 0 | E15: ='shipper master'!C29 -> 0
A16: ='shipper master'!C18 -> 0 | E16: L/C NO.
A17: ='shipper master'!C19 -> 0
A18: PAYMENT METHOD
A19: ='shipper master'!C21 -> NO COMMERCIAL
A20: SHIPPED PER | C20: FROM | E20: TO | K20: VIA
A21: ='shipper master'!C24 -> AIRCRAFT | C21: ='shipper master'!C32 -> TOKYO, JAPAN | F21: ='shipper master'!C33 -> HOCHIMINH-CITY, VIETNAM
A22: C/NO. | B22: ART NO. | C22: DESCRIPTION OF GOODS | D22: COLOR | G22: SIZE | J22: Q'TY | K22: U/PRICE | L22: AMOUNT
B24: ='shipper master'!C36 -> FABRIC & PARTS FOR WEAR & SAMPLE CLOTHES | K24: ='shipper master'!C48 -> F.O.B. TOKYO IN YEN
B26: ='shipper master'!C37 -> 0
J27: ='NARITA '!E106 -> 1267.1 | K27: ='NARITA '!F106 -> M. | L27: ='NARITA '!H106 -> 1351855
B28: ='shipper master'!C38 -> - DETAILS AS PER ATTACHED SHEET - | J28: ='NARITA '!E107 -> 1304 | K28: ='NARITA '!F107 -> PCS. | L28: ='NARITA '!H107 -> 554550
B29: ='shipper master'!C39 -> 0 | J29: ='NARITA '!E108 -> 27 | K29: ='NARITA '!F108 -> SET. | L29: ='NARITA '!H108 -> 2700
B31: TOTAL : | C31: =J27 -> 1267.1 | D31: M. | E31: =J28 -> 1304 | H31: =H29 -> 0 | I31: PCS | J31: =J29 -> 27 | K31: SET. | L31: =SUM(L27:L30) -> 1909105
A34: ='shipper master'!C63 -> " THESE GOODS WILL BE RETURN TO JAPAN | H34: " NO COMMER VALUE | J34: " NO COMMERCIAL VALUE
A35: ='shipper master'!C64 -> AFTER MANUFACTURED AT VIET NAM " | H35: VALUE FOR CUSTOMS PURPOSE ONLY " | J35: VALUE FOR CUSTOMS PURPOSE ONLY "
C36: ='shipper master'!C58 -> 0
A37: ='shipper master'!C60 -> COUNTRY OF ORIGIN : JAPAN
A39: TOTAL CARTONS : | C39: 60CARTONS
A40: TOTAL GROSS WEIGHT : | C40: KGS

Sheet case mark 
A2: ='shipper master'!C49 -> SY-5300419-VT-DD-01 | I2: ='shipper master'!C49 -> SY-5300419-VT-DD-01
A3: ='[1]shipper master'!C50 -> VIVAN GARMENTS VIET NAM | I3: ='[1]shipper master'!C50 -> VIVAN GARMENTS VIET NAM
A4: ='[1]shipper master'!C51 -> COMPANY LIMITED | I4: ='[1]shipper master'!C51 -> COMPANY LIMITED
A5: ='[1]shipper master'!C52 -> HOCHIMINH-CITY, VIETNAM | I5: ='[1]shipper master'!C52 -> HOCHIMINH-CITY, VIETNAM
A6: C/NO. | C6: 1 | I6: C/NO. | K6: 2
A7: ='[1]shipper master'!C54 -> MADE IN JAPAN | I7: ='[1]shipper master'!C54 -> MADE IN JAPAN
A13: ='shipper master'!C49 -> SY-5300419-VT-DD-01 | I13: ='shipper master'!C49 -> SY-5300419-VT-DD-01
A14: ='[1]shipper master'!C50 -> VIVAN GARMENTS VIET NAM | I14: ='[1]shipper master'!C50 -> VIVAN GARMENTS VIET NAM
A15: ='[1]shipper master'!C51 -> COMPANY LIMITED | I15: ='[1]shipper master'!C51 -> COMPANY LIMITED
A16: ='[1]shipper master'!C52 -> HOCHIMINH-CITY, VIETNAM | I16: ='[1]shipper master'!C52 -> HOCHIMINH-CITY, VIETNAM
A17: C/NO. | C17: 3 | I17: C/NO. | K17: 4
A18: ='[1]shipper master'!C54 -> MADE IN JAPAN | I18: ='[1]shipper master'!C54 -> MADE IN JAPAN

Sheet NARITA 
A2: - ATTACHED SHEET -
A4: C/NO. | B4: ART NO. | C4: COLOR | D4: DESCRIPTION OF GOODS | E4: Q'TY | F4: U/PRICE | H4: AMOUNT | I4: 佐川伝票・明細・伝票NO | J4: 搬入日 | K4: 搬入内容 | L4: 数量 | M4: 箱数
B6: (H.S. CODE) | D6: =[2]invoice!B24 -> FABRIC & PARTS FOR WEAR & SAMPLE CLOTHES | G6: ='[1]shipper master'!C48 -> F.O.B. TOKYO IN YEN
D7: MADE IN JAPAN
A8: 1-27 | D8: STYLE: 21SY-60,24A-CS02 | J8: 45390
B9: 007S0052010 | C9: c/#010 BLACK | D9: KNIT FABRIC | E9: 353 | F9: M. | G9: 1030 | H9: =E9*G9 -> 363590 | I9: 入庫NO.22062712
B10: KNIT FABRIC | C10: c/#120 BEIGE | D10: cotton 100% | E10: 23 | F10: M. | G10: 1030 | H10: =E10*G10 -> 23690 | I10: 入庫NO.22062716
B11: パイル編み,後染め | C11: c/#500 BORDEAUX | D11: WIDTH:165CM (450ｇ/㎡ ) | E11: 80.5 | F11: M. | G11: 1030 | H11: =E11*G11 -> 82915
B12: 短繊維、テクスチャード加工無し | C12: c/#103 SMOKEBEIGE | E12: 76 | F12: M. | G12: 1030 | H12: =E12*G12 -> 78280
D14: STYLE: 21SY-60,24A-CS02 | J14: 45390
B15: 007S0052070 | C15: c/#010 BLACK | D15: KNIT FABRIC | E15: 47 | F15: M. | G15: 1120 | H15: =E15*G15 -> 52640
A16: 28-30 | B16: KNIT FABRIC | C16: c/#120 BEIGE | D16: cotton 96% polyurethane 4% | E16: 10 | F16: M. | G16: 1120 | H16: =E16*G16 -> 11200 | I16: 入庫NO.22062714
B17: 後染め フライス編み | C17: c/#500 BORDEAUX | D17: WIDTH:120CM (400ｇ/㎡ ) | E17: 9 | F17: M. | G17: 1120 | H17: =E17*G17 -> 10080 | I17: 入庫NO.22062715
B18: 短繊維、テクスチャード加工無し | C18: c/#103 SMOKEBEIGE | E18: 9 | F18: M. | G18: 1120 | H18: =E18*G18 -> 10080
D20: STYLE: 24A-CS01 | J20: 45390
B21: 027P0003080 | C21: C/#56 BLACK | D21: KNIT FABRIC | E21: 98.3 | F21: M. | G21: 1200 | H21: =E21*G21 -> 117960 | I21: 入庫 No.22062713①
A22: 31-34 | B22: KNIT FABRIC | D22: cotton 100%
B23: パイル編み,後染め | D23: WIDTH:150CM (375ｇ/㎡ )
B24: 短繊維、テクスチャード加工無し
D26: STYLE: 24A-CS01 | J26: 45390
B27: 027P0003080RMG | C27: C/#G | D27: KNIT FABRIC | E27: 95.3 | F27: M. | G27: 1200 | H27: =E27*G27 -> 114360 | I27: 入庫 No.22062713②
A28: 35-38 | B28: KNIT FABRIC | D28: cotton 90% polyester 5% nylon 5%
B29: パイル編み,後染め | D29: WIDTH:150CM (332ｇ/㎡ )
B30: 短繊維、テクスチャード加工無し
D32: STYLE: 24A-PT01/02/03 | J32: 45390
B33: A5100 | C33: C/#521 GRAY | D33: WOVEN FABRIC | E33: 138 | F33: M. | G33: 590 | H33: =E33*G33 -> 81420 | I33: 入庫 No.22062733
A34: 39-40 | B34: WOVEN FABRIC | D34: acetate 100%
B35: 朱子織 後染めサテン生地 | D35: WIDTH:122CM (135ｇ/㎡ )
B36: 長繊維、テクスチャード加工無し
D38: STYLE: 24A-JK01/02 | J38: 45390
B39: 1044309 | C39: C/#00 WHITE | D39: WOVEN FABRIC | E39: 100 | F39: M. | G39: 1200 | H39: =E39*G39 -> 120000 | I39: 入庫 No.22062615
A40: 41-46 | B40: WOVEN FABRIC | C40: C/#09 BLACK | D40: nylon 100% | E40: 200 | F40: M. | G40: 1200 | H40: =E40*G40 -> 240000
B41: 朱子織 後染めサテン生地 | D41: WIDTH:150CM (240ｇ/㎡ )
B42: 長繊維、テクスチャード加工無し
D44: STYLE: bd24-1001/1002 | J44: 45400
B45: 5001-01 | C45: C/#191 WHITE | E45: 52 | F45: PCS. | G45: 457 | H45: =E45*G45 -> 23764 | I45: 入庫No.22063008
A46: 47-48 | B46: men's crew neck T-shirt | C46: C/#165 CHARCOAL | D46: cotton 100% | E46: 48 | F46: PCS. | G46: 457 | H46: =E46*G46 -> 21936
B47: cotton 100%
B48: 短繊維 テクスチャード加工無し
D50: STYLE:AVANI-01 | J50: 45400
B51: men's crew neck used T-shirt | C51: C/#MIX | E51: 60 | F51: PCS. | G51: 500 | H51: =E51*G51 -> 30000 | I51: 入庫No.22063005
A52: 49 | B52: cotton100% | D52: cotton 100%
B53: made in japan
B54: 短繊維 テクスチャード加工無し
A56: 50-57 | D56: 23sy-AC04/05/06 | J56: 45400
B57: men's crew neck used knit wear | C57: C/#MIX | E57: 52 | F57: PCS. | G57: 1000 | H57: =E57*G57 -> 52000 | I57: 入庫No.22063009 | K57: N0.1
B58: cashmere 100% | C58: C/#MIX | D58: cashmere 100% | E58: 51 | F58: PCS. | G58: 1000 | H58: =E58*G58 -> 51000 | K58: N0.2
B59: made in japan | C59: C/#MIX | E59: 44 | F59: PCS. | G59: 1000 | H59: =E59*G59 -> 44000 | K59: N0.3
B60: 長繊維、テクスチャード加工無し | C60: C/#MIX | E60: 46 | F60: PCS. | G60: 1000 | H60: =E60*G60 -> 46000 | K60: N0.4
C61: C/#MIX | E61: 48 | F61: PCS. | G61: 1000 | H61: =E61*G61 -> 48000 | K61: N0.5
C62: C/#MIX | E62: 52 | F62: PCS. | G62: 1000 | H62: =E62*G62 -> 52000 | K62: N0.6
C63: C/#MIX | E63: 54 | F63: PCS. | G63: 1000 | H63: =E63*G63 -> 54000 | K63: N0.7
C64: C/#MIX | E64: 46 | F64: PCS. | G64: 1000 | H64: =E64*G64 -> 46000 | K64: N0.8
A66: 58 | D66: STYLE: 24A-CS01 | J66: 45401
B67: 027P0003100 | C67: C/#G | D67: KNIT FABRIC | E67: 14 | F67: M. | G67: 1630 | H67: =E67*G67 -> 22820
B68: KNIT FABRIC | C68: c/#56 | D68: cotton 100% | E68: 14 | F68: M. | G68: 1630 | H68: =E68*G68 -> 22820
B69: 後染め フライス編み | D69: WIDTH:112CM (515ｇ/㎡ )
B70: 短繊維、テクスチャード加工無し
B72: pattern paper | D72: 24A-JK01 pattern paper | E72: 3 | F72: SET. | G72: 100 | H72: =E72*G72 -> 300
B73: pattern paper | D73: 24A-JK02 pattern paper | E73: 3 | F73: SET. | G73: 100 | H73: =E73*G73 -> 300
B74: pattern paper | D74: 24A-CS01 pattern paper | E74: 3 | F74: SET. | G74: 100 | H74: =E74*G74 -> 300
B75: pattern paper | D75: 21SY-60 pattern paper | E75: 3 | F75: SET. | G75: 100 | H75: =E75*G75 -> 300 | I75: 入庫No.22063009
B76: pattern paper | D76: 24A-SH01 pattern paper | E76: 3 | F76: SET. | G76: 100 | H76: =E76*G76 -> 300
B77: pattern paper | D77: 24A-CS02 pattern paper | E77: 3 | F77: SET. | G77: 100 | H77: =E77*G77 -> 300
B79: men's nylon coat SAMPLE CLOTHES | D79: 24A-JK01 sample | E79: 1 | F79: PCS. | G79: 4000 | H79: =E79*G79 -> 4000
B80: men's nylon vest SAMPLE CLOTHES | D80: 24A-JK02 sample | E80: 1 | F80: PCS. | G80: 3000 | H80: =E80*G80 -> 3000
B81: men's zip parker SAMPLE CLOTHES | D81: 24A-CS01 sample | E81: 1 | F81: PCS. | G81: 2800 | H81: =E81*G81 -> 2800
B82: men's parker SAMPLE CLOTHES | D82: 21SY-60 sample | E82: 1 | F82: PCS. | G82: 2500 | H82: =E82*G82 -> 2500
B83: men's quilting tops SAMPLE CLOTHES | D83: 24A-CS02 sample | E83: 1 | F83: PCS. | G83: 2500 | H83: =E83*G83 -> 2500
B84: men's pocket shirt SAMPLE CLOTHES | D84: 24A-SH01 sample | E84: 1 | F84: PCS. | G84: 2500 | H84: =E84*G84 -> 2500
B85: men's satin pants CLOTHES | D85: 24A-PT01 sample | E85: 1 | F85: PCS. | G85: 2000 | H85: =E85*G85 -> 2000
B86: men's survival satin pants SAMPLE CLOTHES | D86: 24A-PT02 sample | E86: 1 | F86: PCS. | G86: 2500 | H86: =E86*G86 -> 2500
B88: PRESTIGE woven tag | D88: woven tag 材質：ポリエステル100% | E88: 705 | F88: PCS. | G88: 10 | H88: =E88*G88 -> 7050
A90: 59-60 | D90: bd24-1001/1002 | J90: 45404
B91: USED MESH TEE | C91: C/#MIX | E91: 20 | F91: PCS. | G91: 1500 | H91: =E91*G91 -> 30000
B92: KNIT FABRIC
B93: メッシュ生地
B94: 長繊維 プリント有 made in Japan | I94: 佐川454143072541
D96: bd24-1001/1002
B97: USED MESH PANTS | C97: C/#MIX | E97: 18 | F97: PCS. | G97: 1500 | H97: =E97*G97 -> 27000
B98: KNIT FABRIC
B99: メッシュ生地
B100: 長繊維 プリント有 made in Japan
B102: pattern paper | D102: 24A-PT01 pattern paper | E102: 3 | F102: SET. | G102: 100 | H102: =E102*G102 -> 300
B103: pattern paper | D103: 24A-PT02 pattern paper | E103: 3 | F103: SET. | G103: 100 | H103: =E103*G103 -> 300
B104: pattern paper | D104: 24A-PT03 pattern paper | E104: 3 | F104: SET. | G104: 100 | H104: =E104*G104 -> 300
B106: TOTAL : | C106: 60CARTONS | E106: =SUMIF($F$8:$F$104,"M.",$E$8:$E$104) -> 1267.1 | F106: M. | H106: =SUMIF($F$8:$F$104,"M.",$H$8:$H$104) -> 1351855
E107: =SUMIF($F$8:$F$104,"PCS.",$E$8:$E$104) -> 1304 | F107: PCS. | H107: =SUMIF($F$8:$F$104,"PCS.",$H$8:$H$104) -> 554550
E108: =SUMIF($F$8:$F$105,"SET.",$E$8:$E$105) -> 27 | F108: SET. | H108: =SUMIF($F$8:$F$104,"SET.",$H$8:$H$104) -> 2700
H109: =SUM(H106:H108) -> 1909105

Sheet サンプル製品カタログ
D1: ITEM
B2: NAME | C2: color | E2: lady's or men's | F2: WOVEN or KNIT | G2: picture | H2: Composition | I2: packingNo.
B3: 24A-JK01 sample | C3: C/#white | D3: men's nylon coat SAMPLE CLOTHES | E3: men's | F3: WOVEN FABRIC | H3: FRONT nylon100% LINING polyester 100% | I3: 58
B4: 24A-JK02 sample | C4: C/#black | D4: men's nylon vest SAMPLE CLOTHES | E4: men's | F4: WOVEN FABRIC | H4: nylon 100%
B5: 24A-CS01 sample | C5: C/#gray | D5: men's zip parker SAMPLE CLOTHES | E5: men's | F5: KNIT FABRIC | H5: COTTON 100%
B6: 21SY-60 sample | C6: C/#yellow | D6: men's parker SAMPLE CLOTHES | E6: men's | F6: KNIT FABRIC | H6: COTTON 100%
B7: 24A-CS02 sample | C7: C/＃beige | D7: men's quilting tops SAMPLE CLOTHES | E7: men's | F7: WOVEN FABRIC | H7: FRONT COTTON 63% NYLON 37% LINING COTTON 100%
B8: 24A-SH01 sample | C8: C/#white | D8: men's pocket shirt SAMPLE CLOTHES | E8: men's | F8: WOVEN FABRIC | H8: COTTON100%
B9: 24A-PT01 sample | C9: C/＃silver | D9: men's satin pants CLOTHES | E9: men's | F9: WOVEN FABRIC | H9: FRONT ACETATE100% LINING POLYESTER 100%
B10: 24A-PT02 sample | C10: C/#silver | D10: men's survival satin pants SAMPLE CLOTHES | E10: men's | F10: WOVEN FABRIC | H10: FRONT ACETATE100% LINING POLYESTER 100%

Sheet LABEL
A2: LABEL SHEET -
A4: C/NO. | B4: ART NO. | C4: DESCRIPTION OF GOODS | D4: 原産国
A5: 1-27 | C5: STYLE: 21SY-60,24A-CS02
B6: 007S0052010 | C6: KNIT FABRIC
B7: KNIT FABRIC | C7: cotton 100% | D7: MADE IN JAPAN
B8: パイル編み,後染め | C8: WIDTH:165CM (450ｇ/㎡ ) | D8: SHUNYA CO., LTD.
B9: 短繊維、テクスチャード加工無し
A11: C/NO. | B11: ART NO. | C11: DESCRIPTION OF GOODS | D11: 原産国
C12: STYLE: 21SY-60,24A-CS02
B13: 007S0052070 | C13: KNIT FABRIC
A14: 28-30 | B14: KNIT FABRIC | C14: cotton 96% polyurethane 4% | D14: MADE IN JAPAN
B15: 後染め フライス編み | C15: WIDTH:120CM (400ｇ/㎡ ) | D15: SHUNYA CO., LTD.
B16: 短繊維、テクスチャード加工無し
A18: C/NO. | B18: ART NO. | C18: DESCRIPTION OF GOODS | D18: 原産国
C19: STYLE: 24A-CS01
B20: 027P0003080 | C20: KNIT FABRIC
A21: 31-34 | B21: KNIT FABRIC | C21: cotton 100% | D21: MADE IN JAPAN
B22: パイル編み,後染め | C22: WIDTH:150CM (375ｇ/㎡ ) | D22: SHUNYA CO., LTD.
B23: 短繊維、テクスチャード加工無し
A25: C/NO. | B25: ART NO. | C25: DESCRIPTION OF GOODS | D25: 原産国
C26: STYLE: 24A-CS01
B27: 027P0003080RMG | C27: KNIT FABRIC
A28: 35-38 | B28: KNIT FABRIC | C28: cotton 90% polyester 5% nylon 5% | D28: MADE IN JAPAN
B29: パイル編み,後染め | C29: WIDTH:150CM (332ｇ/㎡ ) | D29: SHUNYA CO., LTD.
B30: 短繊維、テクスチャード加工無し
A32: C/NO. | B32: ART NO. | C32: DESCRIPTION OF GOODS | D32: 原産国
C33: STYLE: 24A-PT01/02/03
B34: A5100 | C34: WOVEN FABRIC
A35: 39-40 | B35: WOVEN FABRIC | C35: acetate 100% | D35: MADE IN JAPAN
B36: 朱子織 後染めサテン生地 | C36: WIDTH:122CM (135ｇ/㎡ ) | D36: SHUNYA CO., LTD.
B37: 長繊維、テクスチャード加工無し
A39: C/NO. | B39: ART NO. | C39: DESCRIPTION OF GOODS | D39: 原産国
C40: STYLE: 24A-JK01/02
B41: 1044309 | C41: WOVEN FABRIC
A42: 41-46 | B42: WOVEN FABRIC | C42: nylon 100% | D42: MADE IN JAPAN
B43: 朱子織 後染めサテン生地 | C43: WIDTH:150CM (240ｇ/㎡ ) | D43: SHUNYA CO., LTD.
B44: 長繊維、テクスチャード加工無し
A46: C/NO. | B46: ART NO. | C46: DESCRIPTION OF GOODS | D46: 原産国
C47: STYLE: bd24-1001/1002
B48: 5001-01
A49: 47-48 | B49: men's crew neck T-shirt | C49: cotton 100% | D49: MADE IN JAPAN
B50: cotton 100% | D50: SHUNYA CO., LTD.
B51: 短繊維 テクスチャード加工無し
A53: C/NO. | B53: ART NO. | C53: DESCRIPTION OF GOODS | D53: 原産国
C54: STYLE:AVANI-01
B55: men's crew neck used T-shirt
A56: 49 | B56: cotton100% | C56: cotton 100% | D56: MADE IN JAPAN
B57: made in japan | D57: SHUNYA CO., LTD.
B58: 短繊維 テクスチャード加工無し
A60: C/NO. | B60: ART NO. | C60: DESCRIPTION OF GOODS | D60: 原産国
A61: 50-57 | C61: 23sy-AC04/05/06
B62: men's crew neck knit wear
B63: cashmere 100% | C63: cashmere 100% | D63: MADE IN JAPAN
B64: made in japan | D64: SHUNYA CO., LTD.
B65: 長繊維、テクスチャード加工無し
A71: C/NO. | B71: ART NO. | C71: DESCRIPTION OF GOODS | D71: 原産国
A72: 58 | C72: STYLE: 24A-CS01
B73: 027P0003100 | C73: KNIT FABRIC
B74: KNIT FABRIC | C74: cotton 100%
B75: 後染め フライス編み | C75: WIDTH:112CM (515ｇ/㎡ )
B76: 短繊維、テクスチャード加工無し
B78: pattern paper | C78: 24A-JK01 pattern paper
B79: pattern paper | C79: 24A-JK02 pattern paper
B80: pattern paper | C80: 24A-CS01 pattern paper | D80: MADE IN JAPAN
B81: pattern paper | C81: 21SY-60 pattern paper | D81: SHUNYA CO., LTD.
B82: pattern paper | C82: 24A-SH01 pattern paper
B83: pattern paper | C83: 24A-CS02 pattern paper
B85: men's nylon coat SAMPLE CLOTHES | C85: 24A-JK01 sample
B86: men's nylon vest SAMPLE CLOTHES | C86: 24A-JK02 sample
B87: men's zip parker SAMPLE CLOTHES | C87: 24A-CS01 sample
B88: men's parker SAMPLE CLOTHES | C88: 21SY-60 sample
B89: men's quilting tops SAMPLE CLOTHES | C89: 24A-CS02 sample
B90: men's pocket shirt SAMPLE CLOTHES | C90: 24A-SH01 sample
B91: men's satin pants CLOTHES | C91: 24A-PT01 sample
B92: men's survival satin pants SAMPLE CLOTHES | C92: 24A-PT02 sample
B94: PRESTIGE woven tag | C94: woven tag 材質：ポリエステル100%
A96: C/NO. | B96: ART NO. | C96: DESCRIPTION OF GOODS
A97: 59-60 | C97: bd24-1001/1002 | D97: 原産国
B98: USED MESH TEE
B99: KNIT FABRIC
B100: メッシュ生地
B101: 長繊維 プリント有 made in Japan
C103: bd24-1001/1002
B104: USED MESH PANTS
B105: KNIT FABRIC
B106: メッシュ生地 | D106: MADE IN JAPAN
B107: 長繊維 プリント有 made in Japan | D107: SHUNYA CO., LTD.
B109: pattern paper | C109: 24A-PT01 pattern paper
B110: pattern paper | C110: 24A-PT02 pattern paper
B111: pattern paper | C111: 24A-PT03 pattern paper
