Workbook
Name pricetable: #REF!
Name pricetable: #REF!
Name pricetable: #REF!
Name pricetable: #REF!
Name pricetable: #REF!
Name pricetable: #REF!

Sheet shipper master
A1: 1 | B1: S/CODE | C1: SHIPPER NAME
A2: =A1+1 -> 2 | B2: SHIPPER | C2: SHUNYA CO., LTD.
A3: =A2+1 -> 3 | B3: SHIPPER ADDRESS 1 | C3: KENSHIN BLDG., 1F, 1-22-10 DOUGENZAKA,
A4: =A3+1 -> 4 | B4: SHIPPER ADDRESS 2 | C4: SHIBUYA-KU 150-0043
A5: =A4+1 -> 5 | B5: SHIPPER ADDRESS 3 | C5: TEL : +81(0)3-5459-1177
A6: =A5+1 -> 6 | B6: TEL
A7: =A6+1 -> 7 | B7: FAX
A8: =A7+1 -> 8 | B8: ATTN OR VAT NO.
A9: =A8+1 -> 9 | B9: BUYER | C9: VIVAN GARMENTS VIET NAM COMPANY LIMITED
A10: =A9+1 -> 10 | B10: BUYER ADDRESS1 | C10: D17 Street , Sai Gon South Residential Area
A11: =A10+1 -> 11 | B11: BUYER ADDRESS2 | C11: Hamlet 3 , Long Hau Commune , Can Giuoc District,
A12: =A11+1 -> 12 | B12: BUYER ADDRESS3 | C12: Long An Province , VietNam
A13: =A12+1 -> 13 | B13: TEL/FAX | C13: TEL : ( 084 ) 097 22 00 798 ATTN : MR. TUAN
A14: =A13+1 -> 14 | B14: ATTN
A15: =A14+1 -> 15 | B15: CONSIGNEE : | C15: - SAME AS BUYER -
A16: =A15+1 -> 16 | B16: CONSIGNEE ADDRESS1
A17: =A16+1 -> 17 | B17: CONSIGNEE ADDRESS2
A18: =A17+1 -> 18 | B18: CONSIGNEE ADDRESS3
A19: =A18+1 -> 19 | B19: TEL
A20: =A19+1 -> 20 | B20: FAX
A21: =A20+1 -> 21 | B21: ATTN | C21: NO COMMERCIAL
A22: =A21+1 -> 22 | B22: PAYMENT 1
A23: =A22+1 -> 23 | B23: PAYMENT 2
A24: =A23+1 -> 24 | B24: SHIPPER PER | C24: AIRCRAFT
A25: =A24+1 -> 25 | B25: INVOICE DATE | C25: Nov, 21 2024
A26: =A25+1 -> 26 | B26: INVOICE NO. | C26: SY-6001121-VT-DD-01
A27: =A26+1 -> 27 | B27: CONTRACT NO. | C27: =C26 -> SY-6001121-VT-DD-01
A28: =A27+1 -> 28 | B28: CONTRACT DATE
A29: =A28+1 -> 29 | B29: ORDER DATE
A30: =A29+1 -> 30 | B30: ORDER NO.
A31: =A30+1 -> 31 | B31: L/C DATE
A32: =A31+1 -> 32 | B32: FROM | C32: TOKYO, JAPAN
A33: =A32+1 -> 33 | B33: TO | C33: HOCHIMINH-CITY, VIETNAM
A34: =A33+1 -> 34 | B34: VIA
A35: =A34+1 -> 35 | B35: SHIPPING TERMS | C35: F.O.B. TOKYO IN YEN
A36: =A35+1 -> 36 | B36: TITTLE 1 | C36: FABRIC & PARTS FOR WEAR & SAMPLE CLOTHES
A37: =A36+1 -> 37 | B37: TITTLE 2
A38: =A37+1 -> 38 | B38: ATTACHE | C38: - DETAILS AS PER ATTACHED SHEET -
A39: =A38+1 -> 39 | B39: C/NO.
A40: =A39+1 -> 40 | B40: STYLE NO.
A41: =A40+1 -> 41 | B41: DESCRIPTION
A42: =A41+1 -> 42 | B42: Q'TY CODE
A43: =A42+1 -> 43 | B43: QUANTITY | C43: 3771M 2085PCS. 790SET.
A44: =A43+1 -> 44 | B44: UNIT PRICE
A45: =A44+1 -> 45 | B45: AMOUNT | C45: ='NARITA '!H72 -> 593635
A46: =A45+1 -> 46 | B46: DISCOUNT
A47: =A46+1 -> 47 | B47: DISCOUNT
A48: =A47+1 -> 48 | B48: SHIPPING TERMS | C48: F.O.B. TOKYO IN YEN
A49: =A48+1 -> 49 | B49: CASE MARK1 | C49: =C27 -> SY-6001121-VT-DD-01
A50: =A49+1 -> 50 | B50: CASE MARK2 | C50: VIVAN GARMENTS VIET NAM COMPANY LIMITED
A51: =A50+1 -> 51 | B51: CASE MARK3 | C51: D17 Street , Sai Gon South Residential Area
A52: =A51+1 -> 52 | B52: CASE MARK4 | C52: Hamlet 3 , Long Hau Commune , Can Giuoc District,
A53: =A52+1 -> 53 | B53: CASE MARK5 | C53: Long An Province , VietNam
A54: =A53+1 -> 54 | B54: CASE MARK6 | C54: TEL : : ( 084 ) 097 22 00 798 ATTN : MR. TUAN
A55: =A54+1 -> 55 | B55: TOTAL | C55: 20PACKAGES
A56: =A55+1 -> 56 | B56: MANUFACTURED BY
A57: =A56+1 -> 57
A58: =A57+1 -> 58
A59: =A58+1 -> 59
A60: =A59+1 -> 60 | B60: ORIGIN | C60: COUNTRY OF ORIGIN : JAPAN
A61: =A60+1 -> 61 | B61: OUR BANK
A62: =A61+1 -> 62
A63: =A62+1 -> 63 | B63: 持ち帰り条件 | C63: " THESE GOODS WILL BE RETURN TO JAPAN
A64: =A63+1 -> 64 | C64: AFTER MANUFACTURED AT VIET NAM "
A65: =A64+1 -> 65
A66: =A65+1 -> 66
A67: =A66+1 -> 67 | B67: ETD TYO
A68: =A67+1 -> 68 | B68: DELIVERY SCHEDULES | C68: END OF JUNE - BEG., OF ＭＡＲ, 2018
A69: =A68+1 -> 69 | B69: INSURANCE | C69: COVERED BY SHIPPER
A70: =A69+1 -> 70 | B70: REMARK 1
A71: =A70+1 -> 71
A72: =A71+1 -> 72
A73: =A72+1 -> 73
A74: =A73+1 -> 74
A75: =A74+1 -> 75 | B75: AIR FREIGHT | C75: PREPAID
A76: =A75+1 -> 76 | B76: YOUR (OUR) FORWARDER
A77: =A76+1 -> 77
A78: =A77+1 -> 78 | B78: CUSTOMS AGENT | C78: MEITETSU WORLD TRANSPORT (MR. NAMIKI)
A79: =A78+1 -> 79 | B79: FORWARDER | C79: MEITETSU WORLD TRANSPORT (MR. NAMIKI)
A80: =A79+1 -> 80
A81: =A80+1 -> 81 | B81: C/O ISSUED DATE | C81: Nov, 21 2024
A82: =A81+1 -> 82
A83: =A82+1 -> 83 | B83: COUNTRY | C83: VIETNAM
A84: =A83+1 -> 84
A85: =A84+1 -> 85
A86: =A85+1 -> 86

Sheet case mark 
A2: ='shipper master'!C26 -> SY-6001121-VT-DD-01 | I2: ='shipper master'!C26 -> SY-6001121-VT-DD-01
A3: ='[1]shipper master'!C50 -> VIVAN GARMENTS VIET NAM | I3: ='[1]shipper master'!C50 -> VIVAN GARMENTS VIET NAM
A4: ='[1]shipper master'!C51 -> COMPANY LIMITED | I4: ='[1]shipper master'!C51 -> COMPANY LIMITED
A5: ='[1]shipper master'!C52 -> HOCHIMINH-CITY, VIETNAM | I5: ='[1]shipper master'!C52 -> HOCHIMINH-CITY, VIETNAM
A6: C/NO. | C6: 1 | I6: C/NO. | K6: 2
A7: ='[1]shipper master'!C54 -> MADE IN JAPAN | I7: ='[1]shipper master'!C54 -> MADE IN JAPAN
A13: ='shipper master'!C26 -> SY-6001121-VT-DD-01 | I13: ='shipper master'!C26 -> SY-6001121-VT-DD-01
A14: ='[1]shipper master'!C50 -> VIVAN GARMENTS VIET NAM | I14: ='[1]shipper master'!C50 -> VIVAN GARMENTS VIET NAM
A15: ='[1]shipper master'!C51 -> COMPANY LIMITED | I15: ='[1]shipper master'!C51 -> COMPANY LIMITED
A16: ='[1]shipper master'!C52 -> HOCHIMINH-CITY, VIETNAM | I16: ='[1]shipper master'!C52 -> HOCHIMINH-CITY, VIETNAM
A17: C/NO. | C17: 3 | I17: C/NO. | K17: 4
A18: ='[1]shipper master'!C54 -> MADE IN JAPAN | I18: ='[1]shipper master'!C54 -> MADE IN JAPAN

Sheet invoice
A1: INVOICE
A2: ='[2]shipper master'!C2 -> SHUNYA CO., LTD.
A3: ='[2]shipper master'!C3 -> KENSHIN BLDG., 1F, 1-22-10 DOUGENZAKA,
A4: ='[2]shipper master'!C4 -> SHIBUYA-KU 150-0043 | K4: ='[2]shipper master'!C6 -> 0
A5: ='[2]shipper master'!C5 -> TEL : +81(0)3-5459-1177 | K5: ='[2]shipper master'!C7 -> 0
A6: IMPORTER | E6: INVOICE NO. | K6: CASE MARK
A7: ='[2]shipper master'!C9 -> VIVAN GARMENTS VIET NAM COMPANY LIMITED | E7: ='[2]shipper master'!C26 -> SY-5800906-VT-DD-01
A8: ='[2]shipper master'!C10 -> D17 Street , Sai Gon South Residential Area | E8: INVOICE DATE | K8: ='shipper master'!C26 -> SY-6001121-VT-DD-01
A9: ='[2]shipper master'!C11 -> Hamlet 3 , Long Hau Commune , Can Giuoc District, | E9: ='[2]shipper master'!C25 -> Sep, 06 2024 | K9: ='[1]shipper master'!C50 -> VIVAN GARMENTS VIET NAM
A10: ='[2]shipper master'!C12 -> Long An Province , VietNam | E10: CONTRACT NO. | K10: ='[1]shipper master'!C51 -> COMPANY LIMITED
A11: ='[2]shipper master'!C13 -> TEL : ( 084 ) 097 22 00 798 ATTN : MR. TUAN | E11: ='[2]shipper master'!C27 -> SY-5800906-VT-DD-01 | K11: ='[1]shipper master'!C52 -> HOCHIMINH-CITY, VIETNAM
A12: CONSIGNEE | E12: ORDER NO. | K12: C/NO. 1-20
A13: ='[2]shipper master'!C15 -> - SAME AS BUYER - | E13: ='[2]shipper master'!C30 -> 0 | K13: MADE IN JAPAN
A14: ='[2]shipper master'!C16 -> 0 | E14: ORDER DATE
A15: ='[2]shipper master'!C17 -> 0 | E15: ='[2]shipper master'!C29 -> 0
A16: ='[2]shipper master'!C18 -> 0 | E16: L/C NO.
A17: ='[2]shipper master'!C19 -> 0
A18: PAYMENT METHOD
A19: ='[2]shipper master'!C21 -> NO COMMERCIAL
A20: SHIPPED PER | C20: FROM | E20: TO | K20: VIA
A21: ='[2]shipper master'!C24 -> AIRCRAFT | C21: ='[2]shipper master'!C32 -> TOKYO, JAPAN | F21: ='[2]shipper master'!C33 -> HOCHIMINH-CITY, VIETNAM
A22: C/NO. | B22: ART NO. | C22: DESCRIPTION OF GOODS | D22: COLOR | G22: SIZE | J22: Q'TY | K22: U/PRICE | L22: AMOUNT
B24: ='[2]shipper master'!C36 -> FABRIC & PARTS FOR WEAR & SAMPLE CLOTHES | K24: ='[2]shipper master'!C48 -> F.O.B. TOKYO IN YEN
B26: ='[2]shipper master'!C37 -> 0
J27: ='NARITA '!E69+'NARITA (2)'!E77 -> 3771 | K27: ='[2]NARITA '!F28 -> M. | L27: ='NARITA '!H69+'NARITA (2)'!H77 -> 639776
B28: ='[2]shipper master'!C38 -> - DETAILS AS PER ATTACHED SHEET - | J28: ='NARITA '!E70+'NARITA (2)'!E78 -> 2085 | K28: ='[2]NARITA '!F29 -> PCS. | L28: ='NARITA '!H70+'NARITA (2)'!H78 -> 187608
J29: ='NARITA '!E71+'NARITA (2)'!E79 -> 790 | K29: ='NARITA '!F71 -> SET. | L29: ='NARITA '!H71+'NARITA (2)'!H79 -> 27070
B30: TOTAL : | C30: =J27 -> 3771 | D30: M. | E30: =J28 -> 2085 | H30: =#REF! -> #REF! | I30: PCS. | J30: =J29 -> 790 | K30: SET. | L30: =SUM(L27:L29) -> 854454
A33: ='[2]shipper master'!C63 -> " THESE GOODS WILL BE RETURN TO JAPAN | H33: " NO COMMER VALUE | J33: " NO COMMERCIAL VALUE
A34: ='[2]shipper master'!C64 -> AFTER MANUFACTURED AT VIET NAM " | H34: VALUE FOR CUSTOMS PURPOSE ONLY " | J34: VALUE FOR CUSTOMS PURPOSE ONLY "
C35: ='[2]shipper master'!C58 -> 0
A36: ='[2]shipper master'!C60 -> COUNTRY OF ORIGIN : JAPAN
A38: TOTAL CARTONS : | C38: 20CARTONS
A39: TOTAL GROSS WEIGHT : | C39: KGS

Sheet NARITA 
A2: - ATTACHED SHEET -
A4: C/NO. | B4: ART NO. | C4: COLOR | D4: DESCRIPTION OF GOODS | E4: Q'TY | F4: U/PRICE | H4: AMOUNT | I4: 佐川伝票・明細 | J4: 搬入日 | K4: 伝票NO | L4: 搬入内容 | M4: 数量 | N4: 箱数
B6: (H.S. CODE) | D6: =[3]invoice!B24 -> FABRIC & PARTS FOR WEAR & SAMPLE CLOTHES | G6: ='[1]shipper master'!C48 -> F.O.B. TOKYO IN YEN
D7: MADE IN JAPAN
A8: 1-2 | D8: STYLE: 25S-JK01(24SY-19) | N8: 2
B9: 012S0008298 | C9: C/#099 BLACK | D9: WOVEN FABRIC | E9: 51 | F9: M. | G9: 1040 | H9: =E9*G9 -> 53040
B10: WOVEN FABRIC | C10: c/#204 BEIGE | D10: COTTON 72%、POLYURETHANE28% | E10: 50 | F10: M. | G10: 1040 | H10: =E10*G10 -> 52000 | I10: NO.22068766 | J10: 11/7着
B11: 綾織 ツイル 後染め | D11: WIDTH:140CM (186ｇ/㎡ )
B12: 短繊維、プリント加工なし
A14: 3-4 | D14: STYLE: cc25ss-25, | N14: 2
B15: BL1300 | C15: C/#BK | D15: KNIT FABRIC | E15: 36.5 | F15: M. | G15: 1480 | H15: =E15*G15 -> 54020
B16: KNIT FABRIC | C16: c/#1 | D16: COTTON100% | E16: 38 | F16: M. | G16: 1480 | H16: =E16*G16 -> 56240 | I16: NO.22068731 | J16: 11/7着
B17: 綿メッシュ 丸編み | D17: WIDTH:85WCM (190ｇ/㎡ )
B18: 短繊維、プリント加工なし
A20: 5-6 | D20: STYLE: cc25ss-26/cc25ss-33 | N20: 2
B21: 81-81051 | C21: C/#4 BROWN | D21: WOVEN FABRIC | E21: 22 | F21: M. | G21: 1090 | H21: =E21*G21 -> 23980
B22: WOVEN FABRIC | C22: c/#BK | D22: POLYESTER100% | E22: 10 | F22: M. | G22: 1090 | H22: =E22*G22 -> 10900 | I22: NO.22068730 | J22: 11/7着
B23: 朱子織 サテン 後染め | D23: WIDTH:138CM (128ｇ/㎡ )
B24: 長繊維、プリント加工なし
A26: 7-8 | D26: STYLE: cc25ss-07 | N26: 2
B27: PIN79 | C27: C/#99 BLACK | D27: KNIT FABRIC | E27: 10 | F27: M. | G27: 1310 | H27: =E27*G27 -> 13100
B28: KNIT FABRIC | C28: c/#93 GRAY | D28: POLYESTER100% | E28: 9 | F28: M. | G28: 1310 | H28: =E28*G28 -> 11790 | I28: NO.22068761 | J28: 11/7着
B29: スムース 後染め | D29: WIDTH:140CM (108ｇ/㎡ )
B30: 長繊維、プリント加工なし
A32: 9 | D32: STYLE: 25S-PT03 | N32: 1
B33: BALLOON COTTON 5 | C33: c/#1 WHITE | D33: COTTON YARM | E33: 1 | F33: KG. | G33: 4500 | H33: =E33*G33 -> 4500
D34: COTTON 50% ACRYLIC 50% | I34: NO.22069147 | J34: 11/19着
B36: men's shirt SAMPLE CLOTHES | D36: 25S-SH01 sample | E36: 1 | F36: PCS. | G36: 5000 | H36: =E36*G36 -> 5000
B37: men's wool pants SAMPLE CLOTHES | D37: 25S-PT01 sample | E37: 1 | F37: PCS. | G37: 5000 | H37: =E37*G37 -> 5000
B39: WOVEN NAME | D39: PRESTIGE name | E39: 400 | F39: PCS. | G39: 10 | H39: =E39*G39 -> 4000
A41: 10 | D41: STYLE: 25S-PT03 | N41: 1
B42: lace motif sample | D42: 25S-PT03 sample | E42: 2 | F42: PCS. | G42: 5000 | H42: =E42*G42 -> 10000 | I42: NO.22069257 | J42: 11/21着
A45: 11-14 | D45: STYLE: cc25ss-04/cc25ss-05/cc25ss-06/cc25ss-07 | N45: 4
B46: KKF 2742 | C46: C/#11 WHITE | D46: KNIT FABRIC | E46: 50.5 | F46: M. | G46: 1010 | H46: =E46*G46 -> 51005
B47: KNIT FABRIC | C47: C/#46 GRAY | D47: POLYESTER100% | E47: 55 | F47: M. | G47: 1010 | H47: =E47*G47 -> 55550 | I47: 佐川561400824972 | J47: 11/22着
B48: クサリ 後染め | C48: C/#20 BLACK | D48: WIDTH:140CM (160ｇ/㎡ ) | E48: 51 | F48: M. | G48: 1010 | H48: =E48*G48 -> 51510 | I48: 佐川561400824961
B49: 長繊維、プリント加工なし | I49: 第一貨物60950825154
A51: 15 | D51: STYLE: cc25ss-44 | I51: 佐川457813907246 | N51: 1
B52: used synthetic leather jacket | C52: C/#MIX | E52: 13 | F52: PCS. | G52: 5000 | H52: =E52*G52 -> 65000
B53: 合皮 | J53: 11/22着
B55: pattern paper | D55: cc25ss-04 pattern paper | E55: 2 | F55: SET. | G55: 500 | H55: =E55*G55 -> 1000
B56: pattern paper | D56: cc25ss-05 pattern paper | E56: 2 | F56: SET. | G56: 500 | H56: =E56*G56 -> 1000
B57: pattern paper | D57: cc25ss-06 pattern paper | E57: 2 | F57: SET. | G57: 500 | H57: =E57*G57 -> 1000
B58: pattern paper | D58: cc25ss-23 pattern paper | E58: 1 | F58: SET. | G58: 500 | H58: =E58*G58 -> 500
B59: pattern paper | D59: cc25ss-24 pattern paper | E59: 1 | F59: SET. | G59: 500 | H59: =E59*G59 -> 500
B60: pattern paper | D60: cc25ss-25 pattern paper | E60: 1 | F60: SET. | G60: 500 | H60: =E60*G60 -> 500
B61: pattern paper | D61: cc25ss-45 pattern paper | E61: 1 | F61: SET. | G61: 500 | H61: =E61*G61 -> 500
B62: pattern paper | D62: cc25ss-46 pattern paper | E62: 1 | F62: SET. | G62: 500 | H62: =E62*G62 -> 500
B63: pattern paper | D63: cc25ss-47 pattern paper | E63: 1 | F63: SET. | G63: 500 | H63: =E63*G63 -> 500
B64: pattern paper | D64: cc25ss-60 pattern paper | E64: 1 | F64: SET. | G64: 500 | H64: =E64*G64 -> 500
B66: PRESTIGE WOVEN NAME | E66: 650 | F66: PCS. | G66: 100 | H66: =E66*G66 -> 65000
C69: 15CARTONS | E69: =SUMIF($F$8:$F$66,"M.",$E$8:$E$66) -> 383 | F69: M. | H69: =SUMIF($F$8:$F$66,"M.",$H$8:$H$66) -> 433135
E70: =SUMIF($F$8:$F$66,"PCS.",$E$8:$E$66) -> 1067 | F70: PCS. | H70: =SUMIF($F$8:$F$66,"PCS.",$H$8:$H$66) -> 154000
E71: =SUMIF($F$8:$F$64,"SET.",$E$8:$E$64) -> 13 | F71: SET. | H71: =SUMIF($F$8:$F$66,"SET.",$H$8:$H$66) -> 6500
H72: =SUM(H69:H71) -> 593635

Sheet NARITA (2)
A2: - ATTACHED SHEET -
A4: C/NO. | B4: ART NO. | C4: COLOR | D4: DESCRIPTION OF GOODS | E4: Q'TY | F4: U/PRICE | H4: AMOUNT | I4: 佐川伝票・明細 | J4: 搬入日 | K4: 伝票NO | L4: 搬入内容 | M4: 数量 | N4: 箱数
B6: (H.S. CODE) | D6: ='[4]NARITA '!D6 -> FABRIC & PARTS FOR WEAR & SAMPLE CLOTHES | G6: ='[5]shipper master'!C48 -> F.O.B. TOKYO IN YEN
D7: MADE IN JAPAN
A9: 16-19 | D9: 25S-JK01(24SY-19) | I9: 入庫NO.22068948 | M9: 4
B10: 2002S | D10: POLYESTER LINING POLYESTER100%
D11: #63-23m #BK-23m | E11: 46 | F11: M. | G11: 410 | H11: =E11*G11 -> 18860
B12: 1000 | D12: COTTON 100% PIECE-DYED SLEEK
D13: #128-5m #1-2-5m | E13: 10 | F13: M. | G13: 550 | H13: =E13*G13 -> 5500
B14: KBC9024 | D14: BUCKLE 材質：真鍮
C15: PN | D15: 50MM | E15: 22 | G15: 335 | H15: =E15*G15 -> 7370
C16: PN | D16: 25MM | E16: 44 | F16: PCS. | G16: 165 | H16: =E16*G16 -> 7260
B17: 300 | C17: SPF | D17: EYELET 材質：真鍮 | E17: 250 | F17: SET. | G17: 11 | H17: =E17*G17 -> 2750
D18: PLASTIC BUTTONS
B19: COROZO300 | C19: 405 | D19: 20MM-55 15MM-66 | E19: 121 | F19: PCS. | G19: 16 | H19: =E19*G19 -> 1936
C20: NERO | D20: 20MM-55 15MM-66 | E20: 121 | F20: PCS. | G20: 16 | H20: =E20*G20 -> 1936
B21: OP53 | D21: 11.5MM #40-55 #09-55 | E21: 110 | F21: PCS. | G21: 7 | H21: =E21*G21 -> 770
B22: 5TBH | C22: P-SSL | D22: HOOK 材質：真鍮 | E22: 22 | F22: SET. | G22: 110 | H22: =E22*G22 -> 2420
D24: 25S-PT01/PT02
B25: 500 | D25: COTTON 100% PIECE-DYED SLEEK
D26: #10-68M #24-68M | E26: 136 | F26: M. | G26: 390 | H26: =E26*G26 -> 53040
B27: 3MA C DA | D27: METAL ZIPPER
D28: 13CM #133-88 #580-88 | E28: 176 | F28: PCS. | G28: 80 | H28: =E28*G28 -> 14080
B29: UNCORN775 | D29: PLASTIC BUTTONS
D30: 15MM #42-89 #09-89 | E30: 178 | F30: PCS. | G30: 22 | H30: =E30*G30 -> 3916
B31: B204 | C31: W | D31: ELASTIC WAIST 30MM | E31: 180 | F31: M. | G31: 80 | H31: =E31*G31 -> 14400
B32: PL-S17 | D32: SNAP BUTTONS
D33: #1937-200 #2034-200 | E33: 400 | F33: SET. | G33: 10 | H33: =E33*G33 -> 4000
B34: SIC133 | D34: POLYESTER TAPE 20MM POLYESTER100%
D35: #48-30M #BK-30M | E35: 60 | F35: M. | G35: 110 | H35: =E35*G35 -> 6600
B36: M50 | D36: POLYESTER CORD POLYESTER100%
D37: #76NT-400M #47NT-400M | E37: 800 | F37: M. | G37: 35 | H37: =E37*G37 -> 28000
B38: STAR600 | D38: COTTON TAPE 6MM COTTON100%
D39: #687-800M #BK-800M | E39: 1600 | F39: M. | G39: 30 | H39: =E39*G39 -> 48000
B40: 131-505 | C40: 001 | D40: POLYESTER TAPE 4mm POLYESTER100% | E40: 90 | F40: M. | G40: 25 | H40: =E40*G40 -> 2250
A43: 20 | D43: cc25ss-45 | I43: 入庫NO.22069179 | M43: 1
B44: 2002S | C44: 157 | D44: POLYESTER LINING POLYESTER100% | E44: 17 | F44: M. | G44: 410 | H44: =E44*G44 -> 6970
B46: SB12 | C46: 84NT/BK | D46: THREAD | E46: 3 | F46: SET. | G46: 1800 | H46: =E46*G46 -> 5400
B47: CM5 | C47: 09 | D47: BUTTONS 11.5M,M | E47: 157 | F47: PCS. | G47: 8 | H47: =E47*G47 -> 1256
D49: cc25ss-60
B50: PX EJ24 | C50: 2034 | D50: DOT BUTTONS 15MM | E50: 100 | F50: SET. | G50: 22 | H50: =E50*G50 -> 2200
B51: RP | C51: BK | D51: NYLON TAPE 50MM | E51: 6 | F51: M. | G51: 150 | H51: =E51*G51 -> 900
B52: LB50R | C52: BK | D52: PLASTIC BUCKLE 50MM 材質：プラスチック | E52: 3 | F52: PCS. | G52: 110 | H52: =E52*G52 -> 330
B53: SIC199 | C53: 71 | D53: TAPE 20MM POLYESTER100% | E53: 5 | F53: M. | G53: 150 | H53: =E53*G53 -> 750
D55: cc25ss-07
B56: AZP6517 | C56: N | D56: 8MM 材質：真鍮 | E56: 36 | F56: PCS. | G56: 17 | H56: =E56*G56 -> 612
B57: AZP6516 | C57: N | D57: 8MM 材質：真鍮 | E57: 36 | F57: PCS. | G57: 17 | H57: =E57*G57 -> 612
B58: COTTON PIPING | D58: COTTON PIPING #BK-1ROLL #1181-1ROLL | E58: 2 | F58: SET. | G58: 1900 | H58: =E58*G58 -> 3800
D60: cc25ss-06
B61: 137-610 | D61: COTTON TAPE #005-4M #000-30M #003-30M | E61: 29 | F61: M. | G61: 85 | H61: =E61*G61 -> 2465
B62: F CORD | D62: POLYESTER CORD #84NT-6Ｍ #79NT-50Ｍ ＃02NT-50Ｍ | E62: 106 | F62: M. | G62: 36 | H62: =E62*G62 -> 3816
D64: cc25ss-24
B65: TAKISEI 皿 | C65: KUROCHOU | D65: SHELL BUTTONS 15ＭＭ 白蝶貝 学術名：PINCTA DA MAXIMA | E65: 36 | F65: PCS. | G65: 25 | H65: =E65*G65 -> 900
B66: CCR02 SS | D66: CORD #38C-1M #50C-2M | E66: 3 | F66: M. | G66: 30 | H66: =E66*G66 -> 90
D68: cc25ss-46
B69: B102 | C69: BK | D69: ELASTIC 6C | E69: 240 | F69: M. | G69: 25 | H69: =E69*G69 -> 6000
B70: B21 | C70: BK | D70: ELASTIC WAIST 35MM | E70: 60 | F70: M. | G70: 150 | H70: =E70*G70 -> 9000
D72: cc25ss-47
B73: 5VS OP DA | C73: 580 | D73: METAL ZIPPER 65.5CM | E73: 1 | F73: PCS | G73: 200 | H73: =E73*G73 -> 200
B74: 5VS C DA | C74: 580 | D74: METAL ZIPPER 16CM | E74: 2 | F74: PCS | G74: 150 | H74: =E74*G74 -> 300
B77: TOTAL : | C77: 5CARTONS | E77: =SUMIF($F$9:$F$76,"M.",$E$9:$E$76) -> 3388 | F77: M. | H77: =SUMIF($F$9:$F$76,"M.",$H$9:$H$76) -> 206641
E78: =SUMIF($F$9:$F$76,"PCS.",$E$9:$E$76) -> 1018 | F78: PCS. | H78: =SUMIF($F$9:$F$76,"PCS.",$H$9:$H$76) -> 33608
E79: =SUMIF($F$9:$F$76,"SET.",$E$9:$E$76) -> 777 | F79: SET. | H79: =SUMIF($F$9:$F$76,"SET.",$H$9:$H$76) -> 20570
B80: TOTAL : | G80: TOTAL | H80: =SUM(H9:H76) -> 268689

Sheet サンプル製品カタログ
D1: ITEM
B2: NAME | C2: color | E2: lady's or men's | F2: WOVEN or KNIT | G2: picture | H2: Composition | I2: packingNo.
B3: men's shirt SAMPLE CLOTHES | C3: C/#YELLOW | D3: men's shirt SAMPLE CLOTHES | E3: men's | F3: WOVEN FABRIC | H3: COTTON100% | I3: 9
B4: men's wool pants SAMPLE CLOTHES | C4: C/#BLACK | D4: men's wool pants SAMPLE CLOTHES | E4: men's | F4: WOVEN FABRIC | H4: FRONT WOOL100% | I4: 9
B5: lace motif sample | C5: C/#WHITE | D5: lace motif sample | E5: men's | F5: KNIT FABRIC | H5: COTTON100% | I5: 10
B6: lace motif sample | C6: C/#WHITE | D6: lace motif sample | E6: men's | F6: KNIT FABRIC | H6: COTTON100% | I6: 10

Sheet LABEL
A2: LABEL SHEET -
A4: C/NO. | B4: ART NO. | C4: DESCRIPTION OF GOODS | D4: 原産国
A5: 1-2 | C5: STYLE: 25S-JK01(24SY-19)
B6: 012S0008298 | C6: WOVEN FABRIC | D6: MADE IN JAPAN
B7: WOVEN FABRIC | C7: COTTON 72%、POLYURETHANE28% | D7: SHUNYA CO., LTD.
B8: 綾織 ツイル 後染め | C8: WIDTH:140CM (186ｇ/㎡ )
B9: 短繊維、プリント加工なし
A11: C/NO. | B11: ART NO. | C11: DESCRIPTION OF GOODS | D11: 原産国
A12: 3-4 | C12: STYLE: cc25ss-25,
B13: BL1300 | C13: KNIT FABRIC | D13: MADE IN JAPAN
B14: KNIT FABRIC | C14: COTTON100% | D14: SHUNYA CO., LTD.
B15: 綿メッシュ 丸編み | C15: WIDTH:85WCM (190ｇ/㎡ )
B16: 短繊維、プリント加工なし
A18: C/NO. | B18: ART NO. | C18: DESCRIPTION OF GOODS | D18: 原産国
A19: 5-6 | C19: STYLE: cc25ss-26/cc25ss-33
B20: 81-81051 | C20: WOVEN FABRIC | D20: MADE IN JAPAN
B21: WOVEN FABRIC | C21: POLYESTER100% | D21: SHUNYA CO., LTD.
B22: 朱子織 サテン 後染め | C22: WIDTH:138CM (128ｇ/㎡ )
B23: 長繊維、プリント加工なし
A25: C/NO. | B25: ART NO. | C25: DESCRIPTION OF GOODS | D25: 原産国
A26: 7-8 | C26: STYLE: cc25ss-07
B27: PIN79 | C27: KNIT FABRIC | D27: MADE IN JAPAN
B28: KNIT FABRIC | C28: POLYESTER100% | D28: SHUNYA CO., LTD.
B29: スムース 後染め | C29: WIDTH:140CM (108ｇ/㎡ )
B30: 長繊維、プリント加工なし
A32: C/NO. | B32: ART NO. | C32: DESCRIPTION OF GOODS | D32: 原産国
A33: 9 | C33: STYLE: 25S-PT03
B34: BALLOON COTTON 5 | C34: COTTON YARM
C35: COTTON 50% ACRYLIC 50%
B37: men's shirt SAMPLE CLOTHES | C37: 25S-SH01 sample | D37: MADE IN JAPAN
B38: men's wool pants SAMPLE CLOTHES | C38: 25S-PT01 sample | D38: SHUNYA CO., LTD.
B40: WOVEN NAME | C40: PRESTIGE name
A42: C/NO. | B42: ART NO. | C42: DESCRIPTION OF GOODS | D42: 原産国
A43: 10 | C43: STYLE: 25S-PT03
B44: lace motif sample | C44: 25S-PT03 sample | D44: MADE IN JAPAN
D45: SHUNYA CO., LTD.
A47: C/NO. | B47: ART NO. | C47: DESCRIPTION OF GOODS | D47: 原産国
A48: 11-14 | C48: STYLE: cc25ss-04/cc25ss-05/cc25ss-06/cc25ss-07
B49: KKF 2742 | C49: KNIT FABRIC | D49: MADE IN JAPAN
B50: KNIT FABRIC | C50: POLYESTER100% | D50: SHUNYA CO., LTD.
B51: クサリ 後染め | C51: WIDTH:140CM (160ｇ/㎡ )
B52: 長繊維、プリント加工なし
A54: C/NO. | B54: ART NO. | C54: DESCRIPTION OF GOODS | D54: 原産国
A55: 15 | C55: STYLE: cc25ss-44
B56: used synthetic leather jacket
B57: 合皮
B59: pattern paper | C59: cc25ss-04 pattern paper
B60: pattern paper | C60: cc25ss-05 pattern paper
B61: pattern paper | C61: cc25ss-06 pattern paper | D61: MADE IN JAPAN
B62: pattern paper | C62: cc25ss-23 pattern paper | D62: SHUNYA CO., LTD.
B63: pattern paper | C63: cc25ss-24 pattern paper
B64: pattern paper | C64: cc25ss-25 pattern paper
B65: pattern paper | C65: cc25ss-45 pattern paper
B66: pattern paper | C66: cc25ss-46 pattern paper
B67: pattern paper | C67: cc25ss-47 pattern paper
B68: pattern paper | C68: cc25ss-60 pattern paper
B70: PRESTIGE WOVEN NAME
A72: C/NO. | B72: ART NO. | C72: DESCRIPTION OF GOODS | D72: 原産国
A73: 16-19 | C73: 25S-JK01(24SY-19)
B74: 2002S | C74: POLYESTER LINING POLYESTER100%
C75: #63-23m #BK-23m
B76: 1000 | C76: COTTON 100% PIECE-DYED SLEEK
C77: #128-5m #1-2-5m
B78: KBC9024 | C78: BUCKLE 材質：真鍮
C79: 50MM
C80: 25MM
B81: 300 | C81: EYELET 材質：真鍮
C82: PLASTIC BUTTONS
B83: COROZO300 | C83: 20MM-55 15MM-66
C84: 20MM-55 15MM-66
B85: OP53 | C85: 11.5MM #40-55 #09-55
B86: 5TBH | C86: HOOK 材質：真鍮
C88: 25S-PT01/PT02
B89: 500 | C89: COTTON 100% PIECE-DYED SLEEK
C90: #10-68M #24-68M
B91: 3MA C DA | C91: METAL ZIPPER
C92: 13CM #133-88 #580-88
B93: UNCORN775 | C93: PLASTIC BUTTONS
C94: 15MM #42-89 #09-89 | D94: MADE IN JAPAN
B95: B204 | C95: ELASTIC WAIST 30MM | D95: SHUNYA CO., LTD.
B96: PL-S17 | C96: SNAP BUTTONS
C97: #1937-200 #2034-200
B98: SIC133 | C98: POLYESTER TAPE 20MM POLYESTER100%
C99: #48-30M #BK-30M
B100: M50 | C100: POLYESTER CORD POLYESTER100%
C101: #76NT-400M #47NT-400M
B102: STAR600 | C102: COTTON TAPE 6MM COTTON100%
C103: #687-800M #BK-800M
B104: 131-505 | C104: POLYESTER TAPE 4mm POLYESTER100%
A107: C/NO. | B107: ART NO. | C107: DESCRIPTION OF GOODS | D107: 原産国
A108: 20 | C108: cc25ss-45
B109: 2002S | C109: POLYESTER LINING POLYESTER100%
B111: SB12 | C111: THREAD
B112: CM5 | C112: BUTTONS 11.5M,M
C114: cc25ss-60
B115: PX EJ24 | C115: DOT BUTTONS 15MM
B116: RP | C116: NYLON TAPE 50MM
B117: LB50R | C117: PLASTIC BUCKLE 50MM 材質：プラスチック
B118: SIC199 | C118: TAPE 20MM POLYESTER100%
C120: cc25ss-07
...
