Workbook
Name pricetable: #REF!
Name pricetable: #REF!
Name pricetable: #REF!
Name pricetable: #REF!
Name pricetable: #REF!

Sheet shipper master
A1: 1 | B1: S/CODE | C1: SHIPPER NAME
A2: =A1+1 -> 2 | B2: SHIPPER | C2: SHUNYA CO., LTD.
A3: =A2+1 -> 3 | B3: SHIPPER ADDRESS 1 | C3: KENSHIN BLDG., 1F, 1-22-10 DOUGENZAKA,
A4: =A3+1 -> 4 | B4: SHIPPER ADDRESS 2 | C4: SHIBUYA-KU 150-0043
A5: =A4+1 -> 5 | B5: SHIPPER ADDRESS 3 | C5: TEL : +81(0)3-5459-1177
A6: =A5+1 -> 6 | B6: TEL
A7: =A6+1 -> 7 | B7: FAX
A8: =A7+1 -> 8 | B8: ATTN OR VAT NO.
A9: =A8+1 -> 9 | B9: BUYER | C9: VIVAN GARMENTS VIET NAM COMPANY LIMITED
A10: =A9+1 -> 10 | B10: BUYER ADDRESS1 | C10: D17 Street , Sai Gon South Residential Area
A11: =A10+1 -> 11 | B11: BUYER ADDRESS2 | C11: Hamlet 3 , Long Hau Commune , Can Giuoc District,
A12: =A11+1 -> 12 | B12: BUYER ADDRESS3 | C12: Long An Province , VietNam
A13: =A12+1 -> 13 | B13: TEL/FAX | C13: TEL : ( 084 ) 097 22 00 798 ATTN : MR. TUAN
A14: =A13+1 -> 14 | B14: ATTN
A15: =A14+1 -> 15 | B15: CONSIGNEE : | C15: - SAME AS BUYER -
A16: =A15+1 -> 16 | B16: CONSIGNEE ADDRESS1
A17: =A16+1 -> 17 | B17: CONSIGNEE ADDRESS2
A18: =A17+1 -> 18 | B18: CONSIGNEE ADDRESS3
A19: =A18+1 -> 19 | B19: TEL
A20: =A19+1 -> 20 | B20: FAX
A21: =A20+1 -> 21 | B21: ATTN | C21: NO COMMERCIAL
A22: =A21+1 -> 22 | B22: PAYMENT 1
A23: =A22+1 -> 23 | B23: PAYMENT 2
A24: =A23+1 -> 24 | B24: SHIPPER PER | C24: AIRCRAFT
A25: =A24+1 -> 25 | B25: INVOICE DATE | C25: Dec, 22 2025
A26: =A25+1 -> 26 | B26: INVOICE NO. | C26: SY-7801222-VT-DD-01
A27: =A26+1 -> 27 | B27: CONTRACT NO. | C27: =C26 -> SY-7801222-VT-DD-01
A28: =A27+1 -> 28 | B28: CONTRACT DATE
A29: =A28+1 -> 29 | B29: ORDER DATE
A30: =A29+1 -> 30 | B30: ORDER NO.
A31: =A30+1 -> 31 | B31: L/C DATE
A32: =A31+1 -> 32 | B32: FROM | C32: TOKYO, JAPAN
A33: =A32+1 -> 33 | B33: TO | C33: HOCHIMINH-CITY, VIETNAM
A34: =A33+1 -> 34 | B34: VIA
A35: =A34+1 -> 35 | B35: SHIPPING TERMS | C35: F.O.B. TOKYO IN YEN
A36: =A35+1 -> 36 | B36: TITTLE 1 | C36: FABRIC & PARTS FOR WEAR & SAMPLE CLOTHES
A37: =A36+1 -> 37 | B37: TITTLE 2
A38: =A37+1 -> 38 | B38: ATTACHE | C38: - DETAILS AS PER ATTACHED SHEET -
A39: =A38+1 -> 39 | B39: C/NO.
A40: =A39+1 -> 40 | B40: STYLE NO.
A41: =A40+1 -> 41 | B41: DESCRIPTION
A42: =A41+1 -> 42 | B42: Q'TY CODE
A43: =A42+1 -> 43 | B43: QUANTITY | C43: 687M. 3189PCS. 10KG. 500SET. 25ROLL.
A44: =A43+1 -> 44 | B44: UNIT PRICE
A45: =A44+1 -> 45 | B45: AMOUNT | C45: =invoice!O33 -> 1220920
A46: =A45+1 -> 46 | B46: DISCOUNT
A47: =A46+1 -> 47 | B47: DISCOUNT
A48: =A47+1 -> 48 | B48: SHIPPING TERMS | C48: F.O.B. TOKYO IN YEN
A49: =A48+1 -> 49 | B49: CASE MARK1 | C49: =C27 -> SY-7801222-VT-DD-01
A50: =A49+1 -> 50 | B50: CASE MARK2 | C50: VIVAN GARMENTS VIET NAM COMPANY LIMITED
A51: =A50+1 -> 51 | B51: CASE MARK3 | C51: D17 Street , Sai Gon South Residential Area
A52: =A51+1 -> 52 | B52: CASE MARK4 | C52: Hamlet 3 , Long Hau Commune , Can Giuoc District,
A53: =A52+1 -> 53 | B53: CASE MARK5 | C53: Long An Province , VietNam
A54: =A53+1 -> 54 | B54: CASE MARK6 | C54: TEL : : ( 084 ) 097 22 00 798 ATTN : MR. TUAN
A55: =A54+1 -> 55 | B55: TOTAL | C55: 21PACKAGES
A56: =A55+1 -> 56 | B56: MANUFACTURED BY
A57: =A56+1 -> 57
A58: =A57+1 -> 58
A59: =A58+1 -> 59
A60: =A59+1 -> 60 | B60: ORIGIN | C60: COUNTRY OF ORIGIN : JAPAN,USA
A61: =A60+1 -> 61 | B61: OUR BANK
A62: =A61+1 -> 62
A63: =A62+1 -> 63 | B63: 持ち帰り条件 | C63: " THESE GOODS WILL BE RETURN TO JAPAN
A64: =A63+1 -> 64 | C64: AFTER MANUFACTURED AT VIET NAM "
A65: =A64+1 -> 65
A66: =A65+1 -> 66
A67: =A66+1 -> 67 | B67: ETD TYO
A68: =A67+1 -> 68 | B68: DELIVERY SCHEDULES | C68: END OF JUNE - BEG., OF ＭＡＲ, 2018
A69: =A68+1 -> 69 | B69: INSURANCE | C69: COVERED BY SHIPPER
A70: =A69+1 -> 70 | B70: REMARK 1
A71: =A70+1 -> 71
A72: =A71+1 -> 72
A73: =A72+1 -> 73
A74: =A73+1 -> 74
A75: =A74+1 -> 75 | B75: AIR FREIGHT | C75: PREPAID
A76: =A75+1 -> 76 | B76: YOUR (OUR) FORWARDER
A77: =A76+1 -> 77
A78: =A77+1 -> 78 | B78: CUSTOMS AGENT | C78: MEITETSU WORLD TRANSPORT (MR. NAMIKI)
A79: =A78+1 -> 79 | B79: FORWARDER | C79: MEITETSU WORLD TRANSPORT (MR. NAMIKI)
A80: =A79+1 -> 80
A81: =A80+1 -> 81 | B81: C/O ISSUED DATE | C81: Nov, 13 2025
A82: =A81+1 -> 82
A83: =A82+1 -> 83 | B83: COUNTRY | C83: VIETNAM
A84: =A83+1 -> 84
A85: =A84+1 -> 85
A86: =A85+1 -> 86

Sheet case mark 
A2: ='shipper master'!C26 -> SY-7801222-VT-DD-01 | I2: ='shipper master'!C26 -> SY-7801222-VT-DD-01
A3: ='[1]shipper master'!C50 -> VIVAN GARMENTS VIET NAM | I3: ='[1]shipper master'!C50 -> VIVAN GARMENTS VIET NAM
A4: ='[1]shipper master'!C51 -> COMPANY LIMITED | I4: ='[1]shipper master'!C51 -> COMPANY LIMITED
A5: ='[1]shipper master'!C52 -> HOCHIMINH-CITY, VIETNAM | I5: ='[1]shipper master'!C52 -> HOCHIMINH-CITY, VIETNAM
A6: C/NO. | C6: 1 | I6: C/NO. | K6: 2
A7: ='[1]shipper master'!C54 -> MADE IN JAPAN | I7: ='[1]shipper master'!C54 -> MADE IN JAPAN
A13: ='shipper master'!C26 -> SY-7801222-VT-DD-01 | I13: ='shipper master'!C26 -> SY-7801222-VT-DD-01
A14: ='[1]shipper master'!C50 -> VIVAN GARMENTS VIET NAM | I14: ='[1]shipper master'!C50 -> VIVAN GARMENTS VIET NAM
A15: ='[1]shipper master'!C51 -> COMPANY LIMITED | I15: ='[1]shipper master'!C51 -> COMPANY LIMITED
A16: ='[1]shipper master'!C52 -> HOCHIMINH-CITY, VIETNAM | I16: ='[1]shipper master'!C52 -> HOCHIMINH-CITY, VIETNAM
A17: C/NO. | C17: 3 | I17: C/NO. | K17: 4
A18: ='[1]shipper master'!C54 -> MADE IN JAPAN | I18: ='[1]shipper master'!C54 -> MADE IN JAPAN

Sheet invoice
A1: INVOICE
A2: ='[2]shipper master'!C2 -> SHUNYA CO., LTD.
A3: ='[2]shipper master'!C3 -> KENSHIN BLDG., 1F, 1-22-10 DOUGENZAKA,
A4: ='[2]shipper master'!C4 -> SHIBUYA-KU 150-0043 | N4: ='[2]shipper master'!C6 -> 0
A5: ='[2]shipper master'!C5 -> TEL : +81(0)3-5459-1177 | N5: ='[2]shipper master'!C7 -> 0
A6: IMPORTER | F6: INVOICE NO. | N6: CASE MARK
A7: ='[2]shipper master'!C9 -> VIVAN GARMENTS VIET NAM COMPANY LIMITED | F7: ='shipper master'!C26 -> SY-7801222-VT-DD-01
A8: ='[2]shipper master'!C10 -> D17 Street , Sai Gon South Residential Area | F8: INVOICE DATE | N8: ='shipper master'!C26 -> SY-7801222-VT-DD-01
A9: ='[2]shipper master'!C11 -> Hamlet 3 , Long Hau Commune , Can Giuoc District, | F9: ='shipper master'!C25 -> Dec, 22 2025 | N9: ='[1]shipper master'!C50 -> VIVAN GARMENTS VIET NAM
A10: ='[2]shipper master'!C12 -> Long An Province , VietNam | F10: CONTRACT NO. | N10: ='[1]shipper master'!C51 -> COMPANY LIMITED
A11: ='[2]shipper master'!C13 -> TEL : ( 084 ) 097 22 00 798 ATTN : MR. TUAN | F11: ='shipper master'!C26 -> SY-7801222-VT-DD-01 | N11: ='[1]shipper master'!C52 -> HOCHIMINH-CITY, VIETNAM
A12: CONSIGNEE | F12: ORDER NO. | N12: C/NO. 1-21
A13: ='[2]shipper master'!C15 -> - SAME AS BUYER - | F13: ='[2]shipper master'!C30 -> 0 | N13: MADE IN JAPAN
A14: ='[2]shipper master'!C16 -> 0 | F14: ORDER DATE | N14: MADE IN USA
A15: ='[2]shipper master'!C17 -> 0 | F15: ='[2]shipper master'!C29 -> 0 | N15: MADE IN CHINA
A16: ='[2]shipper master'!C18 -> 0 | F16: L/C NO.
A17: ='[2]shipper master'!C19 -> 0
A18: PAYMENT METHOD
A19: ='[2]shipper master'!C21 -> NO COMMERCIAL
A20: SHIPPED PER | D20: FROM | F20: TO | N20: VIA
A21: ='[2]shipper master'!C24 -> AIRCRAFT | D21: ='[2]shipper master'!C32 -> TOKYO, JAPAN | G21: ='[2]shipper master'!C33 -> HOCHIMINH-CITY, VIETNAM
A22: C/NO. | B22: ART NO. | D22: DESCRIPTION OF GOODS | E22: COLOR | H22: SIZE | M22: Q'TY | N22: U/PRICE | O22: AMOUNT
B24: ='[2]shipper master'!C36 -> FABRIC & PARTS FOR WEAR & SAMPLE CLOTHES | N24: ='[2]shipper master'!C48 -> F.O.B. TOKYO IN YEN
B26: ='[2]shipper master'!C37 -> 0 | M26: ='NARITA '!E71+'NARITA (2)'!E113 -> 687 | N26: M. | O26: ='NARITA '!H71+'NARITA (2)'!H113 -> 579080
M27: ='NARITA '!E72+'NARITA (2)'!E114 -> 3189 | N27: PCS. | O27: ='NARITA '!H72+'NARITA (2)'!H114 -> 567140
M28: ='NARITA '!E73 -> 10 | N28: KG. | O28: ='NARITA '!H73 -> 10000
M29: ='NARITA (2)'!E115 -> 500 | N29: SET. | O29: ='NARITA (2)'!H115 -> 9500
M30: ='NARITA (2)'!E116 -> 25 | N30: ROLL. | O30: ='NARITA (2)'!H116 -> 55200
B31: ='[2]shipper master'!C38 -> - DETAILS AS PER ATTACHED SHEET -
A33: TOTAL : | B33: =M26 -> 687 | C33: M. | D33: =M27 -> 3189 | E33: PCS. | F33: =M28 -> 10 | I33: PCS. | J33: KG. | K33: =M29 -> 500 | L33: =N29 -> SET. | M33: =M30 -> 25 | N33: ROLL. | O33: =SUM(O26:O32) -> 1220920
A36: ='[2]shipper master'!C63 -> " THESE GOODS WILL BE RETURN TO JAPAN | I36: " NO COMMER VALUE | M36: " NO COMMERCIAL VALUE
A37: ='[2]shipper master'!C64 -> AFTER MANUFACTURED AT VIET NAM " | I37: VALUE FOR CUSTOMS PURPOSE ONLY " | M37: VALUE FOR CUSTOMS PURPOSE ONLY "
D38: ='[2]shipper master'!C58 -> 0
A39: ='[2]shipper master'!C60 -> COUNTRY OF ORIGIN : JAPAN
A41: TOTAL CARTONS : | D41: 21CARTONS
A42: TOTAL GROSS WEIGHT : | D42: KGS

Sheet NARITA 
A2: - ATTACHED SHEET -
A4: C/NO. | B4: ART NO. | C4: COLOR | D4: DESCRIPTION OF GOODS | E4: Q'TY | F4: U/PRICE | H4: AMOUNT | I4: 佐川伝票・明細 | J4: 搬入日 | K4: 伝票NO | L4: 搬入内容 | M4: 数量 | N4: 箱数
B6: (H.S. CODE) | D6: =[3]invoice!B24 -> FABRIC & PARTS FOR WEAR & SAMPLE CLOTHES | G6: ='[1]shipper master'!C48 -> F.O.B. TOKYO IN YEN
D7: MADE IN JAPAN
A8: 1-2 | D8: STYLE:26S-PT02(25SY-16) | N8: 2
B9: YG1072 | C9: c/#25 GRAY | D9: KNIT FABRIC | E9: 10 | F9: M. | G9: 1370 | H9: =E9*G9 -> 13700
B10: KNIT FABRIC | C10: c/#5 BLACK | D10: COTTON100% | E10: 19 | F10: M. | G10: 1370 | H10: =E10*G10 -> 26030 | I10: 入庫NO.22077213 | J10: 11/6
B11: 丸編み パイル編 裏毛 後染め | D11: WIDTH:160CM (570ｇ/㎡ )
B12: 短繊維、プリント加工なし
A14: 3-6 | D14: STYLE:26S-SH01(25SY-28),26S-SH02(25SY-19) | N14: 4
B15: 012S0086110 | C15: c/#100 WHITE | D15: WOVEN FABRIC | E15: 174 | F15: M. | G15: 1110 | H15: =E15*G15 -> 193140 | J15: 11/18
B16: WOVEN FABRIC | C16: c/#099 BLACK | D16: COTTON100% | E16: 54 | F16: M. | G16: 1110 | H16: =E16*G16 -> 59940 | I16: 入庫NO.2207491
B17: 平織 先染め タイプライター | D17: WIDTH:145CM (145ｇ/㎡ )
B18: 短繊維、プリント加工なし
A20: 7-8 | D20: STYLE:26S-CS01(25SY-29) | N20: 2
B21: 027G0081935 | C21: c/#G01 GRAY | D21: KNIT FABRIC | E21: 41 | F21: M. | G21: 1020 | H21: =E21*G21 -> 41820
B22: KNIT FABRIC | D22: COTTON100% | I22: 入庫NO.22077572 | J22: 11/21
B23: 丸編みパイル編 裏毛 先染め | D23: WIDTH:180CM (227ｇ/㎡ )
B24: 短繊維、プリント加工なし
A26: 9 | D26: STYLE:cc26ss-22 | N26: 1
B27: 43887 | C27: c/#52 WHITE | D27: KNIT FABRIC | E27: 74 | F27: M. | G27: 880 | H27: =E27*G27 -> 65120
B28: KNIT FABRIC | D28: NYLON100% | I28: 入庫NO.22077600 | J28: 12/1
B29: チュール 後染め | D29: WIDTH:130CM (30ｇ/㎡ )
B30: 長繊維、プリント加工なし
A32: 10-11 | D32: STYLE:cc26ss-52,cc26ss-48,cc26ss-54 | J32: 12/1 | N32: 2
B33: used denim pants | C33: c/#BLUE | D33: WOVEN FABRIC | E33: 74 | F33: PCS. | G33: 1000 | H33: =E33*G33 -> 74000
B34: COTTON 100% | C34: c/#BLACK | E34: 23 | F34: PCS. | G34: 1000 | H34: =E34*G34 -> 23000
B35: 古着
B36: made in USA
D38: STYLE:cc26ss-22 | I38: 入庫NO.2207735
B39: used lace cloth | C39: c/#WHITE | D39: KNIT FABRIC | E39: 10 | F39: KG. | G39: 1000 | H39: =E39*G39 -> 10000
B40: COTTON 100%
B41: 古着
B42: made in JAPAN
A44: 12-14 | D44: STYLE: bd26-001/bd26-004 | N44: 3
B45: 5001-01 | C45: C/#191 WHITE | D45: KNIT FABRIC | E45: 93 | F45: PCS. | G45: 462 | H45: =E45*G45 -> 42966
B46: men's crew neck T-shirt | C46: C/#087 NAVY | D46: COTTON 100% | E46: 59 | F46: PCS. | G46: 462 | H46: =E46*G46 -> 27258 | I46: 入庫NO.22078120 | J46: 12/18
B47: KNIT FABRIC | C47: C/#165 BLACK | D47: made in CHINA | E47: 68 | F47: PCS. | G47: 462 | H47: =E47*G47 -> 31416
B48: 短繊維 天竺 テクスチャード加工無し | C48: c/#369 YELLOW | E48: 1 | F48: PCS. | G48: 462 | H48: =E48*G48 -> 462
A50: 15-17 | D50: STYLE: 26S-CS01,26S-JK01,26S-JK02,26S-JK03,26S-PT02,26S-PT03,26S-PT04,26S-PT05,26S-SH01,26S-SH02,26S-SH03,26S-SH04,26S-TE03 | N50: 3
B51: PRESTIGE plastic bag | C51: c/#CLEAR | E51: 680 | F51: PCS. | G51: 200 | H51: =E51*G51 -> 136000 | I51: 入庫NO.22077921
I52: 入庫NO.22077951 | J52: 12/9
J53: 12/10
A56: 18 | D56: STYLE:574102 | I56: 入庫NO.22078168 | N56: 1
B57: used scarf | C57: C/#MIX | D57: WOVEN FABRIC | E57: 60 | F57: PCS. | G57: 1000 | H57: =E57*G57 -> 60000
B58: COTTON 50% POLYESTER 50%
B59: 古着 プリント有
B60: made in USA
J61: 12/19
D62: STYLE:574102
B63: AKE7046 | C63: c/#701 BEIGE | D63: WOVEN FABRIC | E63: 21 | F63: M. | G63: 990 | H63: =E63*G63 -> 20790
B64: WOVEN FABRIC | C64: c/#1 BLACK | D64: CUPRA55% POLYESTER45% | E64: 26 | F64: M. | G64: 990 | H64: =E64*G64 -> 25740
B65: 綾織 後染め ツイル | D65: WIDTH:122CM (112ｇ/㎡ )
B66: 長繊維、プリント加工なし
D68: STYLE: 26S-CS01,26S-JK01,26S-JK02,26S-JK03,26S-PT02,26S-PT03,26S-PT04,26S-PT05,26S-SH01,26S-SH02,26S-SH03,26S-SH04,26S-TE03
B69: PRESTIGE paper hang tag | D69: PRESTIGE hang tag | E69: 720 | F69: PCS. | G69: 50 | H69: =E69*G69 -> 36000
E71: =SUMIF($F$8:$F$70,"M.",$E$8:$E$70) -> 419 | F71: M. | H71: =SUMIF($F$8:$F$70,"M.",$H$8:$H$70) -> 446280
E72: =SUMIF($F$8:$F$70,"PCS.",$E$8:$E$70) -> 1778 | F72: PCS. | H72: =SUMIF($F$8:$F$70,"PCS.",$H$8:$H$70) -> 431102
E73: =SUMIF($F$8:$F$70,"KG.",$E$8:$E$70) -> 10 | F73: KG. | H73: =SUMIF($F$8:$F$70,"KG.",$H$8:$H$70) -> 10000
B74: TOTAL : | C74: 18CARTONS | G74: TOTAL | H74: =SUM(H8:H70) -> 887382

Sheet NARITA (2)
A2: - ATTACHED SHEET -
A4: C/NO. | B4: ART NO. | C4: COLOR | D4: DESCRIPTION OF GOODS | E4: Q'TY | F4: U/PRICE | H4: AMOUNT | I4: 佐川伝票・明細 | J4: 搬入日 | K4: 伝票NO | L4: 搬入内容 | M4: 数量 | N4: 箱数
B6: (H.S. CODE) | D6: ='[4]NARITA '!D6 -> FABRIC & PARTS FOR WEAR & SAMPLE CLOTHES | G6: ='[5]shipper master'!C48 -> F.O.B. TOKYO IN YEN
D7: MADE IN JAPAN
A9: 19-21 | D9: STYLE：26S-PT01(25SY-17) | I9: 佐川 4529-7621-8295 | N9: 3
B10: 5RA C DA8 | D10: metal ZIPPER
D11: 19CM #560-12 #580-12 | E11: 24 | F11: PCS. | G11: 55 | H11: 1320
D12: 20CM #560-13 #580-13 | E12: 26 | F12: PCS. | G12: 57 | H12: 1482
B13: 3YGRDS C GSN8 | D13: metal ZIPPER | F13: PCS.
D14: 100CM #560-4 #580-4 | E14: 8 | F14: PCS. | G14: 315 | H14: 2520
D15: 102CM #560-8 #580-8 | E15: 16 | F15: PCS. | G15: 320 | H15: 5120
D16: 104CM #560-8 #580-8 | E16: 16 | F16: PCS. | G16: 325 | H16: 5200
D17: 106CM #560-5 #580-5 | E17: 10 | F17: PCS. | G17: 330 | H17: 3300
B18: 15BURR E 2779-2910 | C18: NSL | D18: BURR 素材：真鍮 | E18: 300 | F18: SET. | G18: 15 | H18: 4500
D19: STYLE：26S-PT02(25SY-16)
B20: 3YGRDS C GSN8 | D20: metal ZIPPER
D21: 19CM #560-5 #580-10 | E21: 15 | F21: PCS. | G21: 86 | H21: 1290
D22: 20CM #560-5 #580-10 | E22: 15 | F22: PCS. | G22: 88 | H22: 1320
B23: Ｂ204 | C23: Ｗ | D23: WAIST ELASTIC (30M) 素材：ポリエステル 芯：ポリウレタン | E23: 1 | F23: ROLL. | G23: 2700 | H23: 2700
D25: STYLE：26S-PT03(25SY-21)
B26: 5RA OP DA8 | D26: metal ZIPPER
D27: 74CM #580-4 #572-4 #061-2 | E27: 10 | F27: PCS. | G27: 146 | H27: 1460
D28: 77CM #580-12 #572-8 #061-2 | E28: 22 | F28: PCS. | G28: 150 | H28: 3300
D29: 80CM #580-18 #572-8 #061-2 | E29: 28 | F29: PCS. | G29: 153 | H29: 4284
B31: 5RA OP DA8 | D31: metal ZIPPER
D32: 66.5CM #580-4 #572-4 #061-2 | E32: 10 | F32: PCS. | G32: 138 | H32: 1380
D33: 68CM #580-12 #572-8 #061-2 | E33: 22 | F33: PCS. | G33: 139 | H33: 3058
D34: 69.5CM #580-18 #572-8 #061-2 | E34: 28 | F34: PCS. | G34: 140 | H34: 3920
B35: B204 | C35: Ｗ | D35: WAIST ELASTIC (30M) 素材：ポリエステル 芯：ポリウレタン | E35: 1 | F35: ROLL. | G35: 2700 | H35: 2700
B36: A400 | D36: (SV)CHIPD CORD 200CM 素材：アクリル 先端チップ素材：真鍮
D37: #31-34 #10-20 #6-6 | E37: 60 | F37: PCS. | G37: 295 | H37: 17700
B38: SIC3140 2.5MM | D38: ELASTIC CORD (50M) 素材：ポリエステル100% | J38: 12/22
D39: #50-1 #70-1 | E39: 2 | F39: ROLL. | G39: 2300 | H39: 4600
D40: #132 | E40: 4 | F40: M. | G40: 90 | H40: 360
B41: AST1018 | C41: 09 | D41: STOPPER 素材：ナイロン/ステンレス | E41: 60 | F41: PCS. | G41: 50 | H41: 3000
D42: STYLE：26S-PT05(25SY-39)
B43: 1000 | D43: COTTON 100% PIECE-DYED SLEEK 平織
D44: #3-19 #1-2-26 #5-8 | E44: 53 | F44: M. | G44: 550 | H44: 29150
B45: 3MA C DA | D45: metal ZIPPER 16CM
D46: #551-25 #580-35 #087-10 | E46: 70 | F46: PCS. | G46: 80 | H46: 5600
B47: 22208 M | D47: CORD (50M) 素材：アクリル100%
D48: #9-2 #31-3 #8-1 | E48: 6 | F48: ROLL. | G48: 1600 | H48: 9600
D49: #9 | E49: 5 | F49: M. | G49: 70 | H49: 350
B50: B204 | C50: Ｗ | D50: WAIST ELASTIC 30MM (30M) 素材：ポリエステル 芯：ポリウレタン | E50: 5 | F50: ROLL. | G50: 2700 | H50: 13500
B51: UNUT | D51: BUTTONS 材質：ユリア樹脂
D52: #01-51 #09-71 #43-21 | E52: 145 | F52: PCS. | G52: 10 | H52: 1450
D53: STYLE：26S-JK01(25SY-22)
B54: 2002S | D54: LINING 素材：ポリエステル100% 綾織ツイル 先染め
D55: #45-23 #BK-29 #301-6 | E55: 58 | F55: M. | G55: 420 | H55: 24360
B56: 1000 | D56: COTTON 100% PIECE-DYED SLEEK
D57: #224-6 #1-2-8 #15-2 | E57: 16 | F57: M. | G57: 580 | H57: 9280
B58: 5RA M DA8*DA8 | D58: metal ZIPPER
D59: 54.5CM #334-4 #580-3 #344-1 | E59: 8 | F59: PCS. | G59: 140 | H59: 1120
D60: 56CM #334-8 #580-11 #344-2 | E60: 21 | F60: PCS. | G60: 142 | H60: 2982
D61: 57.5CM #334-8 #580-11 #344-2 | E61: 21 | F61: PCS. | G61: 145 | H61: 3045
D62: STYLE：26S-CS01(25SY-29)
B63: 5RA M DA8*DA8 | D63: metal ZIPPER
D64: 56.5CM #181-2 #580-2 #274-2 | E64: 6 | F64: PCS. | G64: 150 | H64: 900
D65: 58CM #181-12 #580-12 #274-4 | E65: 28 | F65: PCS. | G65: 152 | H65: 4256
D66: 59.5CM #181-16 #580-16 #274-4 | E66: 36 | F66: PCS. | G66: 155 | H66: 5580
B67: A500 | D67: CORD (50M) 素材：アクリル100%
D68: #33-1 #BK-1 #50-1 | E68: 3 | F68: ROLL. | G68: 1900 | H68: 5700
D69: STYLE：26S-JK03(25SY-38)
B70: CXE3000 | D70: LINING 素材：ポリエステル100% メッシュ 先染め
D71: #BK-51 #4-17 #5-33 | E71: 101 | F71: M. | G71: 580 | H71: 58580
B72: 5RA OP DA8 | D72: metal ZIPPER
D73: 60CM #580-4 #257-2 #181-2 | E73: 8 | F73: PCS. | G73: 130 | H73: 1040
D74: 61.5CM #580-14 #257-4 #181-10 | E74: 28 | F74: PCS. | G74: 132 | H74: 3696
D75: 63CM #580-12 #257-4 #181-8 | E75: 24 | F75: PCS. | G75: 135 | H75: 3240
B76: B204 | C76: Ｗ | D76: WAIST ELASTIC 35MM (30M) 素材：ポリエステル 芯：ポリウレタン | E76: 3 | F76: ROLL. | G76: 3000 | H76: 9000
D77: STYLE：26S-JK02(25SY-23)
B78: 5RA C DA8 | D78: metal ZIPPER
D79: 20.5CM #580-2 #572-1 #061-1 | E79: 4 | F79: PCS. | G79: 60 | H79: 240
D80: 21CM #580-6 #572-4 #061-1 | E80: 11 | F80: PCS. | G80: 62 | H80: 682
D81: 21.5CM #580-8 #572-6 #061-1 | E81: 15 | F81: PCS. | G81: 64 | H81: 960
B82: 5RA OP DA8 | D82: 38CM #580-2 #572-1 #061-1 | E82: 4 | F82: PCS. | G82: 105 | H82: 420
D83: 40CM #580-6 #572-4 #061-1 | E83: 11 | F83: PCS. | G83: 107 | H83: 1177
D84: 42CM #580-8 #572-6 #061-1 | E84: 15 | F84: PCS. | G84: 110 | H84: 1650
B85: 5RA OP DA8(R) | D85: 44CM #580-2 #572-1 #061-1 | E85: 4 | F85: PCS. | G85: 112 | H85: 448
D86: 46CM #580-6 #572-4 #061-1 | E86: 11 | F86: PCS. | G86: 115 | H86: 1265
D87: 48CM #580-8 #572-6 #061-1 | E87: 15 | F87: PCS. | G87: 117 | H87: 1755
B88: 5RA OP DA8(L) | D88: 44CM #580-2 #572-1 #061-1 | E88: 4 | F88: PCS. | G88: 112 | H88: 448
D89: 46CM #580-6 #572-4 #061-1 | E89: 11 | F89: PCS. | G89: 115 | H89: 1265
D90: 48CM #580-8 #572-6 #061-1 | E90: 15 | F90: PCS. | G90: 117 | H90: 1755
B91: PX M 24L | D91: DOT BUTTONS 素材：真鍮
D92: #1458-100 #2002-100 | E92: 200 | F92: SET. | G92: 25 | H92: 5000
B93: PACKING | D93: W-100 BK-100 素材：ポリエステル100% | E93: 200 | F93: PCS. | G93: 4 | H93: 800
D94: STYLE：26S-PT04(25SY-37)
B95: 5RA C DA8 | D95: metal ZIPPER
D96: 19CM #580-35 #257-5 #181-10 | E96: 50 | F96: PCS. | G96: 55 | H96: 2750
D97: 12CM #580-35 #257-5 #181-10 | E97: 50 | F97: PCS. | G97: 48 | H97: 2400
B98: B204 | C98: Ｗ | D98: WAIST ELASTIC 30MM (30M) 素材：ポリエステル 芯：ポリウレタン | E98: 2 | F98: ROLL. | G98: 2700 | H98: 5400
B99: RO-3 | C99: BK | D99: CORD 185CM 素材：アクリル100% | E99: 100 | F99: PCS. | G99: 200 | H99: 20000
D100: STYLE：cc25ss-22
B101: 2001 | C101: S2 | D101: LINING 素材：ポリエステル100% 綾織ツイル 先染め | E101: 20 | F101: M. | G101: 345 | H101: 6900
B102: AZP6540F | C102: N | D102: 8MM | E102: 42 | F102: PCS. | G102: 20 | H102: 840
B103: AZP6541F | C103: N | D103: 8MM | E103: 42 | F103: PCS. | G103: 20 | H103: 840
B104: PIPING | D104: 14MM #1127 66M | E104: 1 | F104: ROLL. | G104: 2000 | H104: 2000
B105: S30 | C105: OW | D105: 10MM 60M | E105: 1 | F105: ROLL.
D106: STYLE：cc25ss-60
...

Sheet LABEL
A2: LABEL SHEET -
A4: C/NO. | B4: ART NO. | C4: DESCRIPTION OF GOODS | D4: 原産国
A5: 1-2 | C5: STYLE:26S-PT02(25SY-16)
B6: YG1072 | C6: KNIT FABRIC | D6: MADE IN JAPAN
B7: KNIT FABRIC | C7: COTTON100% | D7: SHUNYA CO., LTD.
B8: 丸編み パイル編 裏毛 後染め | C8: WIDTH:160CM (570ｇ/㎡ )
B9: 短繊維、プリント加工なし
A11: C/NO. | B11: ART NO. | C11: DESCRIPTION OF GOODS | D11: 原産国
A12: 3-6 | C12: STYLE:26S-SH01(25SY-28),26S-SH02(25SY-19)
B13: 012S0086110 | C13: WOVEN FABRIC | D13: MADE IN JAPAN
B14: WOVEN FABRIC | C14: COTTON100% | D14: SHUNYA CO., LTD.
B15: 平織 先染め タイプライター | C15: WIDTH:145CM (145ｇ/㎡ )
B16: 短繊維、プリント加工なし
A18: C/NO. | B18: ART NO. | C18: DESCRIPTION OF GOODS | D18: 原産国
A19: 7-8 | C19: STYLE:26S-CS01(25SY-29)
B20: 027G0081935 | C20: KNIT FABRIC | D20: MADE IN JAPAN
B21: KNIT FABRIC | C21: COTTON100% | D21: SHUNYA CO., LTD.
B22: 丸編みパイル編 裏毛 先染め | C22: WIDTH:180CM (227ｇ/㎡ )
B23: 短繊維、プリント加工なし
A25: C/NO. | B25: ART NO. | C25: DESCRIPTION OF GOODS | D25: 原産国
A26: 9 | C26: STYLE:cc26ss-22
B27: 43887 | C27: KNIT FABRIC | D27: MADE IN JAPAN
B28: KNIT FABRIC | C28: NYLON100% | D28: SHUNYA CO., LTD.
B29: チュール 後染め | C29: WIDTH:130CM (30ｇ/㎡ )
B30: 長繊維、プリント加工なし
A32: C/NO. | B32: ART NO. | C32: DESCRIPTION OF GOODS | D32: 原産国
A33: 10-11 | C33: STYLE:cc26ss-52,cc26ss-48,cc26ss-54
B34: used denim pants | C34: WOVEN FABRIC
B35: COTTON 100%
B36: 古着
B37: made in USA | D37: MADE IN U.S.A
D38: MADE IN JAPAN
C39: STYLE:cc26ss-22 | D39: SHUNYA CO., LTD.
B40: used lace cloth | C40: KNIT FABRIC
B41: COTTON 100%
B42: 古着
B43: made in JAPAN
A45: C/NO. | B45: ART NO. | C45: DESCRIPTION OF GOODS | D45: 原産国
A46: 12-14 | C46: STYLE: bd26-001/bd26-004
B47: 5001-01 | C47: KNIT FABRIC | D47: MADE IN CHINA
B48: men's crew neck T-shirt | C48: COTTON 100% | D48: SHUNYA CO., LTD.
B49: KNIT FABRIC
B50: 短繊維 天竺 テクスチャード加工無し
A52: C/NO. | B52: ART NO. | C52: DESCRIPTION OF GOODS | D52: 原産国
A53: 15-17 | C53: STYLE: 26S-CS01,26S-JK01,26S-JK02,26S-JK03,26S-PT02,26S-PT03,26S-PT04,26S-PT05,26S-SH01,26S-SH02,26S-SH03,26S-SH04,26S-TE03
B54: PRESTIGE plastic bag | D54: MADE IN JAPAN
D55: SHUNYA CO., LTD.
A59: C/NO. | B59: ART NO. | C59: DESCRIPTION OF GOODS | D59: 原産国
A60: 18 | C60: STYLE:574102
B61: used scarf | C61: WOVEN FABRIC
B62: COTTON 50% POLYESTER 50%
B63: 古着 プリント有
B64: made in USA | D64: MADE IN U.S.A
D65: MADE IN JAPAN
C66: STYLE:574102 | D66: SHUNYA CO., LTD.
B67: AKE7046 | C67: WOVEN FABRIC
B68: WOVEN FABRIC | C68: CUPRA55% POLYESTER45%
B69: 綾織 後染め ツイル | C69: WIDTH:122CM (112ｇ/㎡ )
B70: 長繊維、プリント加工なし
C72: STYLE: 26S-CS01,26S-JK01,26S-JK02,26S-JK03,26S-PT02,26S-PT03,26S-PT04,26S-PT05,26S-SH01,26S-SH02,26S-SH03,26S-SH04,26S-TE03
B73: PRESTIGE paper hang tag | C73: PRESTIGE hang tag
A75: C/NO. | B75: ART NO. | C75: DESCRIPTION OF GOODS | D75: 原産国
A76: 19-21 | C76: STYLE：26S-PT01(25SY-17)
B77: 5RA C DA8 | C77: metal ZIPPER
C78: 19CM #560-12 #580-12
C79: 20CM #560-13 #580-13
B80: 3YGRDS C GSN8 | C80: metal ZIPPER
C81: 100CM #560-4 #580-4
C82: 102CM #560-8 #580-8
C83: 104CM #560-8 #580-8
C84: 106CM #560-5 #580-5
B85: 15BURR E 2779-2910 | C85: BURR 素材：真鍮
C86: STYLE：26S-PT02(25SY-16)
B87: 3YGRDS C GSN8 | C87: metal ZIPPER
C88: 19CM #560-5 #580-10
C89: 20CM #560-5 #580-10 | D89: MADE IN JAPAN
B90: Ｂ204 | C90: WAIST ELASTIC (30M) 素材：ポリエステル 芯：ポリウレタン | D90: SHUNYA CO., LTD.
C92: STYLE：26S-PT03(25SY-21)
B93: 5RA OP DA8 | C93: metal ZIPPER
C94: 74CM #580-4 #572-4 #061-2
C95: 77CM #580-12 #572-8 #061-2
C96: 80CM #580-18 #572-8 #061-2
B98: 5RA OP DA8 | C98: metal ZIPPER
C99: 66.5CM #580-4 #572-4 #061-2
C100: 68CM #580-12 #572-8 #061-2
C101: 69.5CM #580-18 #572-8 #061-2
B102: B204 | C102: WAIST ELASTIC (30M) 素材：ポリエステル 芯：ポリウレタン
B103: A400 | C103: (SV)CHIPD CORD 200CM 素材：アクリル 先端チップ素材：真鍮
C104: #31-34 #10-20 #6-6
B105: SIC3140 2.5MM | C105: ELASTIC CORD (50M) 素材：ポリエステル100%
C106: #50-1 #70-1
C107: #132
B108: AST1018 | C108: STOPPER 素材：ナイロン/ステンレス
C109: STYLE：26S-PT05(25SY-39)
B110: 1000 | C110: COTTON 100% PIECE-DYED SLEEK 平織
C111: #3-19 #1-2-26 #5-8
B112: 3MA C DA | C112: metal ZIPPER 16CM
C113: #551-25 #580-35 #087-10
B114: 22208 M | C114: CORD (50M) 素材：アクリル100%
C115: #9-2 #31-3 #8-1
...
