Workbook
Name pricetable: #REF!
Name pricetable: #REF!
Name pricetable: #REF!
Name pricetable: #REF!
Name pricetable: #REF!

Sheet shipper master
A1: 1 | B1: S/CODE | C1: SHIPPER NAME
A2: =A1+1 -> 2 | B2: SHIPPER | C2: SHUNYA CO., LTD.
A3: =A2+1 -> 3 | B3: SHIPPER ADDRESS 1 | C3: KENSHIN BLDG., 1F, 1-22-10 DOUGENZAKA,
A4: =A3+1 -> 4 | B4: SHIPPER ADDRESS 2 | C4: SHIBUYA-KU 150-0043
A5: =A4+1 -> 5 | B5: SHIPPER ADDRESS 3 | C5: TEL : +81(0)3-5459-1177
A6: =A5+1 -> 6 | B6: TEL
A7: =A6+1 -> 7 | B7: FAX
A8: =A7+1 -> 8 | B8: ATTN OR VAT NO.
A9: =A8+1 -> 9 | B9: BUYER | C9: VIVAN GARMENTS VIET NAM COMPANY LIMITED
A10: =A9+1 -> 10 | B10: BUYER ADDRESS1 | C10: D17 Street , Sai Gon South Residential Area
A11: =A10+1 -> 11 | B11: BUYER ADDRESS2 | C11: Hamlet 3 , Long Hau Commune , Can Giuoc District,
A12: =A11+1 -> 12 | B12: BUYER ADDRESS3 | C12: Long An Province , VietNam
A13: =A12+1 -> 13 | B13: TEL/FAX | C13: TEL : ( 084 ) 097 22 00 798 ATTN : MR. TUAN
A14: =A13+1 -> 14 | B14: ATTN
A15: =A14+1 -> 15 | B15: CONSIGNEE : | C15: - SAME AS BUYER -
A16: =A15+1 -> 16 | B16: CONSIGNEE ADDRESS1
A17: =A16+1 -> 17 | B17: CONSIGNEE ADDRESS2
A18: =A17+1 -> 18 | B18: CONSIGNEE ADDRESS3
A19: =A18+1 -> 19 | B19: TEL
A20: =A19+1 -> 20 | B20: FAX
A21: =A20+1 -> 21 | B21: ATTN | C21: NO COMMERCIAL
A22: =A21+1 -> 22 | B22: PAYMENT 1
A23: =A22+1 -> 23 | B23: PAYMENT 2
A24: =A23+1 -> 24 | B24: SHIPPER PER | C24: AIRCRAFT
A25: =A24+1 -> 25 | B25: INVOICE DATE | C25: JUN, 4 2026
A26: =A25+1 -> 26 | B26: INVOICE NO. | C26: SY-8100604VT-DD-01
A27: =A26+1 -> 27 | B27: CONTRACT NO. | C27: =C26 -> SY-8100604VT-DD-01
A28: =A27+1 -> 28 | B28: CONTRACT DATE
A29: =A28+1 -> 29 | B29: ORDER DATE
A30: =A29+1 -> 30 | B30: ORDER NO.
A31: =A30+1 -> 31 | B31: L/C DATE
A32: =A31+1 -> 32 | B32: FROM | C32: TOKYO, JAPAN
A33: =A32+1 -> 33 | B33: TO | C33: HOCHIMINH-CITY, VIETNAM
A34: =A33+1 -> 34 | B34: VIA
A35: =A34+1 -> 35 | B35: SHIPPING TERMS | C35: F.O.B. TOKYO IN YEN
A36: =A35+1 -> 36 | B36: TITTLE 1 | C36: FABRIC & PARTS FOR WEAR & SAMPLE CLOTHES
A37: =A36+1 -> 37 | B37: TITTLE 2
A38: =A37+1 -> 38 | B38: ATTACHE | C38: - DETAILS AS PER ATTACHED SHEET -
A39: =A38+1 -> 39 | B39: C/NO.
A40: =A39+1 -> 40 | B40: STYLE NO.
A41: =A40+1 -> 41 | B41: DESCRIPTION
A42: =A41+1 -> 42 | B42: Q'TY CODE
A43: =A42+1 -> 43 | B43: QUANTITY | C43: 296.5M. 3426PCS.
A44: =A43+1 -> 44 | B44: UNIT PRICE
A45: =A44+1 -> 45 | B45: AMOUNT | C45: =invoice!O31 -> 492959
A46: =A45+1 -> 46 | B46: DISCOUNT
A47: =A46+1 -> 47 | B47: DISCOUNT
A48: =A47+1 -> 48 | B48: SHIPPING TERMS | C48: F.O.B. TOKYO IN YEN
A49: =A48+1 -> 49 | B49: CASE MARK1 | C49: =C27 -> SY-8100604VT-DD-01
A50: =A49+1 -> 50 | B50: CASE MARK2 | C50: VIVAN GARMENTS VIET NAM COMPANY LIMITED
A51: =A50+1 -> 51 | B51: CASE MARK3 | C51: D17 Street , Sai Gon South Residential Area
A52: =A51+1 -> 52 | B52: CASE MARK4 | C52: Hamlet 3 , Long Hau Commune , Can Giuoc District,
A53: =A52+1 -> 53 | B53: CASE MARK5 | C53: Long An Province , VietNam
A54: =A53+1 -> 54 | B54: CASE MARK6 | C54: TEL : : ( 084 ) 097 22 00 798 ATTN : MR. TUAN
A55: =A54+1 -> 55 | B55: TOTAL | C55: 10PACKAGES
A56: =A55+1 -> 56 | B56: MANUFACTURED BY
A57: =A56+1 -> 57
A58: =A57+1 -> 58
A59: =A58+1 -> 59
A60: =A59+1 -> 60 | B60: ORIGIN | C60: COUNTRY OF ORIGIN : JAPAN
A61: =A60+1 -> 61 | B61: OUR BANK
A62: =A61+1 -> 62
A63: =A62+1 -> 63 | B63: 持ち帰り条件 | C63: " THESE GOODS WILL BE RETURN TO JAPAN
A64: =A63+1 -> 64 | C64: AFTER MANUFACTURED AT VIET NAM "
A65: =A64+1 -> 65
A66: =A65+1 -> 66
A67: =A66+1 -> 67 | B67: ETD TYO
A68: =A67+1 -> 68 | B68: DELIVERY SCHEDULES | C68: END OF JUNE - BEG., OF MAR, 2018
A69: =A68+1 -> 69 | B69: INSURANCE | C69: COVERED BY SHIPPER
A70: =A69+1 -> 70 | B70: REMARK 1
A71: =A70+1 -> 71
A72: =A71+1 -> 72
A73: =A72+1 -> 73
A74: =A73+1 -> 74
A75: =A74+1 -> 75 | B75: AIR FREIGHT | C75: PREPAID
A76: =A75+1 -> 76 | B76: YOUR (OUR) FORWARDER
A77: =A76+1 -> 77
A78: =A77+1 -> 78 | B78: CUSTOMS AGENT | C78: MEITETSU WORLD TRANSPORT (MR. NAMIKI)
A79: =A78+1 -> 79 | B79: FORWARDER | C79: MEITETSU WORLD TRANSPORT (MR. NAMIKI)
A80: =A79+1 -> 80
A81: =A80+1 -> 81 | B81: C/O ISSUED DATE | C81: =C25 -> JUN, 4 2026
A82: =A81+1 -> 82
A83: =A82+1 -> 83 | B83: COUNTRY | C83: VIETNAM
A84: =A83+1 -> 84
A85: =A84+1 -> 85
A86: =A85+1 -> 86

Sheet case mark 
A2: ='shipper master'!C26 -> SY-8100604VT-DD-01 | I2: ='shipper master'!C26 -> SY-8100604VT-DD-01
A3: ='[2]shipper master'!C50 -> VIVAN GARMENTS VIET NAM | I3: ='[2]shipper master'!C50 -> VIVAN GARMENTS VIET NAM
A4: ='[2]shipper master'!C51 -> COMPANY LIMITED | I4: ='[2]shipper master'!C51 -> COMPANY LIMITED
A5: ='[2]shipper master'!C52 -> HOCHIMINH-CITY, VIETNAM | I5: ='[2]shipper master'!C52 -> HOCHIMINH-CITY, VIETNAM
A6: C/NO. | C6: 1 | I6: C/NO. | K6: 2
A7: ='[2]shipper master'!C54 -> MADE IN JAPAN | I7: ='[2]shipper master'!C54 -> MADE IN JAPAN
A13: ='shipper master'!C26 -> SY-8100604VT-DD-01 | I13: ='shipper master'!C26 -> SY-8100604VT-DD-01
A14: ='[2]shipper master'!C50 -> VIVAN GARMENTS VIET NAM | I14: ='[2]shipper master'!C50 -> VIVAN GARMENTS VIET NAM
A15: ='[2]shipper master'!C51 -> COMPANY LIMITED | I15: ='[2]shipper master'!C51 -> COMPANY LIMITED
A16: ='[2]shipper master'!C52 -> HOCHIMINH-CITY, VIETNAM | I16: ='[2]shipper master'!C52 -> HOCHIMINH-CITY, VIETNAM
A17: C/NO. | C17: 3 | I17: C/NO. | K17: 4
A18: ='[2]shipper master'!C54 -> MADE IN JAPAN | I18: ='[2]shipper master'!C54 -> MADE IN JAPAN

Sheet invoice
A1: INVOICE
A2: ='[3]shipper master'!C2 -> SHUNYA CO., LTD.
A3: ='[3]shipper master'!C3 -> KENSHIN BLDG., 1F, 1-22-10 DOUGENZAKA,
A4: ='[3]shipper master'!C4 -> SHIBUYA-KU 150-0043 | N4: ='[3]shipper master'!C6 -> 0
A5: ='[3]shipper master'!C5 -> TEL : +81(0)3-5459-1177 | N5: ='[3]shipper master'!C7 -> 0
A6: IMPORTER | F6: INVOICE NO. | N6: CASE MARK
A7: ='[3]shipper master'!C9 -> VIVAN GARMENTS VIET NAM COMPANY LIMITED | F7: ='shipper master'!C26 -> SY-8100604VT-DD-01
A8: ='[3]shipper master'!C10 -> D17 Street , Sai Gon South Residential Area | F8: INVOICE DATE | N8: =F7 -> SY-8100604VT-DD-01
A9: ='[3]shipper master'!C11 -> Hamlet 3 , Long Hau Commune , Can Giuoc District, | F9: ='shipper master'!C25 -> JUN, 4 2026 | N9: VIVAN GARMENTS VIET NAM
A10: ='[3]shipper master'!C12 -> Long An Province , VietNam | F10: CONTRACT NO. | N10: COMPANY LIMITED
A11: ='[3]shipper master'!C13 -> TEL : ( 084 ) 097 22 00 798 ATTN : MR. TUAN | F11: ='shipper master'!C26 -> SY-8100604VT-DD-01 | N11: ='[2]shipper master'!C52 -> HOCHIMINH-CITY, VIETNAM
A12: CONSIGNEE | F12: ORDER NO. | N12: C/NO. 1-10
A13: ='[3]shipper master'!C15 -> - SAME AS BUYER - | F13: ='[3]shipper master'!C30 -> 0 | N13: MADE IN JAPAN
A14: ='[3]shipper master'!C16 -> 0 | F14: ORDER DATE
A15: ='[3]shipper master'!C17 -> 0 | F15: ='[3]shipper master'!C29 -> 0
A16: ='[3]shipper master'!C18 -> 0 | F16: L/C NO.
A17: ='[3]shipper master'!C19 -> 0
A18: PAYMENT METHOD
A19: ='[3]shipper master'!C21 -> NO COMMERCIAL
A20: SHIPPED PER | D20: FROM | F20: TO | N20: VIA
A21: ='[3]shipper master'!C24 -> AIRCRAFT | D21: ='[3]shipper master'!C32 -> TOKYO, JAPAN | G21: ='[3]shipper master'!C33 -> HOCHIMINH-CITY, VIETNAM
A22: C/NO. | B22: ART NO. | D22: DESCRIPTION OF GOODS | E22: COLOR | H22: SIZE | M22: Q'TY | N22: U/PRICE | O22: AMOUNT
B24: ='[3]shipper master'!C36 -> FABRIC & PARTS FOR WEAR & SAMPLE CLOTHES | N24: ='[3]shipper master'!C48 -> F.O.B. TOKYO IN YEN
B26: - DETAILS AS PER ATTACHED SHEET - | M26: =SUM(ATTACHED!E116) -> 296.5 | N26: M. | O26: =SUM(ATTACHED!H116) -> 120205
M27: =SUM(ATTACHED!E117) -> 3426 | N27: PCS. | O27: =SUM(ATTACHED!H117) -> 372754
M28: =ATTACHED!E118 -> 0 | O28: =ATTACHED!H118 -> 0
B31: TOTAL : | E31: =M26 -> 296.5 | J31: M. | K31: =K29 -> 0 | L31: =M27 -> 3426 | M31: PCS. | O31: =SUM(O26:O30) -> 492959
A34: ='[3]shipper master'!C63 -> " THESE GOODS WILL BE RETURN TO JAPAN | I34: " NO COMMER VALUE | M34: " NO COMMERCIAL VALUE
A35: ='[3]shipper master'!C64 -> AFTER MANUFACTURED AT VIET NAM " | I35: VALUE FOR CUSTOMS PURPOSE ONLY " | M35: VALUE FOR CUSTOMS PURPOSE ONLY "
D36: ='[3]shipper master'!C58 -> 0
A37: ='shipper master'!C60 -> COUNTRY OF ORIGIN : JAPAN
A39: TOTAL CARTONS : | D39: 10 CARTONS
A40: TOTAL GROSS WEIGHT : | D40: KGS

Sheet ATTACHED
A2: - ATTACHED SHEET -
A4: C/NO. | B4: ART NO. | C4: COLOR | D4: DESCRIPTION OF GOODS | E4: Q'TY | F4: U/PRICE | H4: AMOUNT | I4: 佐川伝票・明細 | J4: 搬入日 | K4: 伝票NO | L4: 搬入内容 | M4: 数量 | N4: 箱数
B5: (H.S. CODE) | D5: =[1]invoice!B24 -> FABRIC & PARTS FOR WEAR & SAMPLE CLOTHES | F5: ='[2]shipper master'!C48 -> F.O.B. TOKYO IN YEN
D6: MADE IN JAPAN
A7: 1-3 | D7: STYLE:26SY-11 | N7: 3
B8: 11487 | C8: C/#801 ベビーピンク | D8: WOVEN FABRIC | E8: 52 | F8: M. | G8: 390 | H8: =E8*G8 -> 20280 | I8: 入庫NO.22081274 | J8: 5/27
B9: WOVEN FABRIC | C9: C/#503 スカイブルー | D9: COTTON 100% | E9: 52 | F9: M. | G9: 390 | H9: =E9*G9 -> 20280
B10: 平織 ツイル 後染め | C10: C/#301 イエロー | D10: WIDTH:110CM (155ｇ/㎡ ) | E10: 53 | F10: M. | G10: 390 | H10: =E10*G10 -> 20670
B11: 短繊維 プリント加工なし
A13: 4-5 | D13: STYLE:bd26-009 | N13: 2
B14: 5001-01 | C14: C/#001 WHITE | D14: KNIT FABRIC | E14: 44 | F14: PCS. | G14: 672 | H14: =E14*G14 -> 29568 | I14: 入庫NO.22081349 | J14: 5/29
B15: men's crew neck T-shirt | C15: C/#165 BLACK | D15: COTTON 100% | E15: 32 | F15: PCS. | G15: 747 | H15: =E15*G15 -> 23904
B16: KNIT FABRIC | C16: C/#086 NAVY | D16: MADE IN CHINA | E16: 29 | F16: PCS. | G16: 747 | H16: =E16*G16 -> 21663
B17: 短繊維 天竺 テクスチャード加工無し
A19: 6-7 | D19: STYLE:bd26-008 | N19: 2
B20: 4488-01 | C20: C/#002 BLACK | D20: KNIT FABRIC | E20: 35 | F20: PCS. | G20: 1867 | H20: =E20*G20 -> 65345 | I20: 入庫NO.22081349 | J20: 5/29
B21: men's cardigan | C21: C/#005 GRAY | D21: COTTON 100% | E21: 32 | F21: PCS. | G21: 1867 | H21: =E21*G21 -> 59744
B22: KNIT FABRIC | C22: C/#086 NAVY | D22: MADE IN CHINA | E22: 20 | F22: PCS. | G22: 1867 | H22: =E22*G22 -> 37340
B23: 短繊維 天竺 テクスチャード加工無し
A25: 8 | D25: STYLE:25I-CS02 | I25: 入庫NO.2208448 | J25: 6/4 | N25: 1
B26: YG1001 | C26: C/#1 WHITE | D26: KNIT FABRIC | E26: 1 | F26: M. | G26: 1210 | H26: =E26*G26 -> 1210
B27: KNIT FABRIC | D27: COTTON 100%
B28: 丸編み フレンチパイル編み 後染め | D28: WIDTH:180CM (590ｇ/㎡ )
B29: 短繊維、プリント加工なし
D30: STYLE:25I-CS02
B31: YG1002 | C31: C/#1 WHITE | D31: KNIT FABRIC | E31: 0.5 | F31: M. | G31: 990 | H31: =E31*G31 -> 495
B32: KNIT FABRIC | D32: COTTON 95% PU 5%
B33: 丸編み リブ編み 後染め | D33: WIDTH:42WCM (300ｇ/㎡ )
B34: 短繊維、プリント加工なし
D35: STYLE:26A-AC09
B36: GN-13-16 | C36: C/#NICKEL | D36: Metal O-Ring | E36: 100 | F36: PCS. | G36: 170 | H36: =E36*G36 -> 17000
B37: 材質：メタル | D37: 16mm
D39: STYLE:26A-PT-01,26A-PT-02,26A-SH-01,26A-SH-02,26A-JK-01,26A-JK-02,26A-AC-04
B40: PRESTIGE Product bags | C40: c/#CLEAR | D40: PRESTIGE Product bags | E40: 399 | F40: PCS. | G40: 100 | H40: =E40*G40 -> 39900
B41: 材質：ポリエチレン
B42: PRESTIGE Product hang tag | D42: PRESTIGE Product hang tag | E42: 399 | F42: PCS. | G42: 50 | H42: =E42*G42 -> 19950
B44: 26SY-07(26A-SH01) sample | D44: men's cotton shirt SAMPLE CLOTHES | E44: 1 | F44: PCS. | G44: 2000 | H44: =E44*G44 -> 2000
B45: 26SY-06(26A-JK04) sample | D45: men's Velour jacket SAMPLE CLOTHES | E45: 1 | F45: PCS. | G45: 2000 | H45: =E45*G45 -> 2000
A47: 9-10 | D47: EN-22SY-66 | I47: 入庫NO.2208447 | N47: 2
B48: SB17 | C48: C/#BK | D48: BUTTONS 13MM | E48: 246 | F48: PCS. | G48: 18 | H48: =E48*G48 -> 4428
B49: shell button | D49: BUTTONS 10MM | E49: 71 | F49: PCS. | G49: 10 | H49: =E49*G49 -> 710
B50: 学術名： Tectus maximus / 黒蝶
B52: KOHAZE | C52: C/#NICKEL | D52: KINTEN BUJI | E52: 1000 | F52: PCS. | G52: 12 | H52: =E52*G52 -> 12000
B53: 材質：真鍮 | D53: USE：SLEEVE CUFF FASTENING
D54: SHAPE：HALF-MOON SHAPED
B56: 3450 | C56: C/#BK | D56: CORD S | E56: 39 | F56: M. | G56: 80 | H56: =E56*G56 -> 3120
B57: 材質：ポリエステル
B58: PL-S17 | C58: C/#BK | D58: DOT BUTTONS | E58: 100 | F58: PCS. | G58: 10 | H58: =E58*G58 -> 1000
B59: 材質：真鍮
B60: PACKING | C60: C/#BK | D60: 9*3 | E60: 200 | F60: PCS. | G60: 5 | H60: =E60*G60 -> 1000
B61: 材質：ポリエステル
B62: 5YNR C DA8 | C62: C/#580 | D62: ZIPPER 12CM-10PCS. 13CM-50PCS. 14CM-10PCS. | E62: 70 | F62: PCS. | G62: 85 | H62: =E62*G62 -> 5950
B63: 材質：樹脂
D65: EN-22SY-65
B66: 5RGK OP DA8 | C66: C/#580 | D66: ZIPPER
B67: 材質：樹脂 | D67: 38CM-20PCS. 39CM-10PCS. 40CM-30PCS. 41CM-20PCS. | E67: 80 | F67: PCS. | G67: 170 | H67: =E67*G67 -> 13600
B69: 5RGK C DA8 | C69: C/#580 | D69: 16CM-10PCS. 17CM -20PCS. 18CM-10PCS. | E69: 40 | F69: PCS. | G69: 86 | H69: =E69*G69 -> 3440
B70: 材質：樹脂 | C70: C/#258 | D70: COTTON 100% PIECE-DYED SLEEK | E70: 20 | F70: M | G70: 650 | H70: =E70*G70 -> 13000
B71: テープ：平織、白染め：無し
D72: EN-22SY-53
B73: 7989 | C73: C/#999 | D73: MESH LINING | E73: 29 | F73: M. | G73: 600 | H73: =E73*G73 -> 17400
B74: KNIT FABRIC | D74: POLYESTER 100%
B75: 経編み メッシュ 後染め | D75: WIDTH:122CM (140ｇ/㎡ )
B76: 長繊維、プリント加工なし
D78: CC26AW-46
B79: 1000 | C79: C/#26 BEIGE | D79: COTTON 100% PIECE-DYED SLEEK | E79: 8 | F79: M. | G79: 550 | H79: =E79*G79 -> 4400
B80: 綾織 スレキ 先染め | C80: C/#4 GRAY | E80: 5 | F80: M. | G80: 550 | H80: =E80*G80 -> 2750
B81: 短繊維 プリント加工なし | C81: C/#1-2 BLACK | E81: 3 | F81: M. | G81: 550 | H81: =E81*G81 -> 1650
B83: 5RGKB C DA8 | D83: ZIPPER
B84: 材質：樹脂 | C84: C/#563 | D84: 43CM-5PCS. 45CM-5PCS. | E84: 10 | F84: PCS. | G84: 150 | H84: =E84*G84 -> 1500
C85: C/#564 | D85: 43CM-3PCS. 45CM-3PCS. | E85: 6 | F85: PCS. | G85: 150 | H85: =E85*G85 -> 900
C86: C/#580 | D86: 45CM 4PCS. | E86: 4 | F86: PCS. | G86: 150 | H86: =E86*G86 -> 600
B88: 9900 | C88: C/#258 Natural | D88: COTTON 100% PIECE-DYED SLEEK | E88: 20 | F88: M. | G88: 650 | H88: =E88*G88 -> 13000
B89: 綾織 スレキ 先染め
B90: 短繊維 プリント加工なし
B92: 3MGKB C DA8 | D92: ZIPPER
B93: 材質：樹脂 | C93: C/#563 | D93: 16CM-10PCS. 17CM-10PCS. | E93: 20 | F93: PCS. | G93: 65 | H93: =E93*G93 -> 1300
C94: C/#564 | D94: 16CM-6PCS. 17CM-6PCS. | E94: 12 | F94: PCS. | G94: 65 | H94: =E94*G94 -> 780
C95: C/#580 | D95: 17CM-8PCS. | E95: 8 | F95: PCS. | G95: 65 | H95: =E95*G95 -> 520
B97: 132-723 | D97: TAPE
B98: 材質：綿 | D98: 15MM #010-6M #074-4M #050-3M | E98: 13 | F98: M. | G98: 350 | H98: =E98*G98 -> 4550
D99: 12MM #010-2M #074-2M #050-1M | E99: 5 | F99: M. | G99: 320 | H99: =E99*G99 -> 1600
D101: NF25SY-44
B102: PRV26 | C102: C/#33 | D102: BUTTONS 11.5MM | E102: 442 | F102: PCS. | G102: 11 | H102: =E102*G102 -> 4862
B103: 材質：ユリア樹脂
D105: NF25SY-43
B106: 1000 | C106: C/#258 L.BEIGE | D106: COTTON 100% PIECE-DYED SLEEK | E106: 16 | F106: M. | G106: 550 | H106: =E106*G106 -> 8800
B107: 綾織 スレキ 先染め
B108: 短繊維 プリント加工なし
B110: 3MA-C GSN8 | D110: ZIPPER
B111: 材質：樹脂 | C111: C/#572 | D111: 15CM-4PCS. 16CM-4PCS. | E111: 8 | F111: PCS. | G111: 70 | H111: =E111*G111 -> 560
C112: C/#580 | D112: 15CM-8PCS. 16CM-9PCS. | E112: 17 | F112: PCS. | G112: 70 | H112: =E112*G112 -> 1190
E116: =SUMIF($F$7:$F$115,"M.",$E$7:$E$115) -> 296.5 | F116: M. | H116: =SUMIF($F$7:$F$115,"M.",$H$7:$H$115) -> 120205
E117: =SUMIF($F$7:$F$115,"PCS.",$E$7:$E$115) -> 3426 | F117: PCS. | H117: =SUMIF($F$7:$F$115,"PCS.",$H$7:$H$115) -> 372754
B119: TOTAL : | C119: 10 CARTONS | G119: TOTAL | H119: =SUM(H116:H117) -> 492959

Sheet サンプル製品カタログ
D1: ITEM
B2: NAME | C2: color | E2: lady's or men's | F2: WOVEN or KNIT | G2: picture | H2: Composition | I2: packingNo.
B3: men's cotton shirt SAMPLE CLOTHES | C3: BLUE | D3: 26SY-07(26A-SH01) sample | E3: men's | F3: WOVEN | H3: COTTON 100% | I3: 8
B4: men's Velour jacket SAMPLE CLOTHES | C4: BLACK | D4: 26SY-06(26A-JK04) sample | E4: men's | F4: WOVEN | H4: COTTON 70% POLYESTER 30%

Sheet LABEL
A2: LABEL SHEET -
A4: C/NO. | B4: ART NO. | C4: DESCRIPTION OF GOODS | D4: 原産国
A5: 1-3 | C5: STYLE:26SY-11
B6: 11487 | C6: WOVEN FABRIC | D6: MADE IN JAPAN SHUNYA CO., LTD.
B7: WOVEN FABRIC | C7: COTTON 100%
B8: 平織 ツイル 後染め | C8: WIDTH:110CM (155ｇ/㎡ )
B9: 短繊維 プリント加工なし
A11: C/NO. | B11: ART NO. | C11: DESCRIPTION OF GOODS | D11: 原産国
A12: 4-5 | C12: STYLE:bd26-009
B13: 5001-01 | C13: KNIT FABRIC | D13: MADE IN JAPAN SHUNYA CO., LTD.
B14: men's crew neck T-shirt | C14: COTTON 100%
B15: KNIT FABRIC
B16: 短繊維 天竺 テクスチャード加工無し
A18: C/NO. | B18: ART NO. | C18: DESCRIPTION OF GOODS | D18: 原産国
A19: 6-7 | C19: STYLE:bd26-008
B20: 4488-01 | C20: KNIT FABRIC | D20: MADE IN JAPAN SHUNYA CO., LTD.
B21: men's cardigan | C21: COTTON 100%
B22: KNIT FABRIC
B23: 短繊維 天竺 テクスチャード加工無し
A25: C/NO. | B25: ART NO. | C25: DESCRIPTION OF GOODS | D25: 原産国
A26: 8 | C26: STYLE:25I-CS02
B27: YG1001 | C27: KNIT FABRIC | D27: MADE IN JAPAN SHUNYA CO., LTD.
B28: KNIT FABRIC | C28: COTTON 100%
B29: 丸編み フレンチパイル編み 後染め | C29: WIDTH:180CM (590ｇ/㎡ )
B30: 短繊維、プリント加工なし
A32: C/NO. | B32: ART NO. | C32: DESCRIPTION OF GOODS | D32: 原産国
A33: 8 | C33: STYLE:25I-CS02
B34: YG1002 | C34: KNIT FABRIC | D34: MADE IN JAPAN SHUNYA CO., LTD.
B35: KNIT FABRIC | C35: COTTON 95% PU 5%
B36: 丸編み リブ編み 後染め | C36: WIDTH:42WCM (300ｇ/㎡ )
B37: 短繊維、プリント加工なし
A39: C/NO. | B39: ART NO. | C39: DESCRIPTION OF GOODS | D39: 原産国
A40: 8 | C40: STYLE:26A-AC09
B41: GN-13-16 | C41: Metal O-Ring | D41: MADE IN JAPAN SHUNYA CO., LTD.
B42: 材質：メタル | C42: 16mm
A46: C/NO. | B46: ART NO. | C46: DESCRIPTION OF GOODS | D46: 原産国
A47: 8 | C47: STYLE:26A-PT-01,26A-PT-02,26A-SH-01,26A-SH-02,26A-JK-01,26A-JK-02,26A-AC-04
B48: PRESTIGE Product bags | C48: PRESTIGE Product bags | D48: MADE IN JAPAN SHUNYA CO., LTD.
B49: PRESTIGE Product hang tag | C49: PRESTIGE Product hang tag
A53: C/NO. | B53: ART NO. | C53: DESCRIPTION OF GOODS | D53: 原産国
A54: 8 | C54: STYLE:26SY-07(26A-SH01),26SY-06(26A-JK04)
B55: 26SY-07(26A-SH01) sample | C55: men's cotton shirt SAMPLE CLOTHES | D55: MADE IN JAPAN SHUNYA CO., LTD.
B56: 26SY-06(26A-JK04) sample | C56: men's Velour jacket SAMPLE CLOTHES
A59: C/NO. | B59: ART NO. | C59: DESCRIPTION OF GOODS | D59: 原産国
A60: 9-10 | C60: EN-22SY-66 | D60: MADE IN JAPAN SHUNYA CO., LTD.
B61: SB17 | C61: BUTTONS 13MM
B62: shell button | C62: BUTTONS 10MM
B63: 学術名： Tectus maximus / 黒蝶
B65: KOHAZE | C65: KINTEN BUJI
B66: 材質：真鍮
B67: 3450 | C67: CORD S
B68: 材質：ポリエステル
B69: PL-S17 | C69: DOT BUTTONS
B70: 材質：真鍮
B71: PACKING | C71: 9*3
B72: 材質：ポリエステル
B73: 5YNR C DA8 | C73: ZIPPER 12CM-10PCS. 13CM-50PCS. 14CM-10PCS.
B74: 材質：樹脂
C76: EN-22SY-65
B77: 5RGK OP DA8 | C77: ZIPPER
B78: 材質：樹脂 | C78: 38CM-20PCS. 39CM-10PCS. 40CM-30PCS. 41CM-20PCS.
B80: 5RGK C DA8 | C80: 16CM-10PCS. 17CM -20PCS. 18CM-10PCS.
B81: 材質：樹脂 | C81: COTTON 100% PIECE-DYED SLEEK
C83: EN-22SY-53
B84: 7989 | C84: MESH LINING
B85: KNIT FABRIC | C85: POLYESTER 100%
B86: 丸編み フレンチパイル編み 後染め | C86: WIDTH:122CM (ｇ/㎡ )
B87: 短繊維、プリント加工なし
C89: CC26AW-46
B90: 1000 | C90: COTTON 100% PIECE-DYED SLEEK
B91: 綾織 スレキ 先染め | C91: #26-8M #4-5M #1-2-3M
B92: 短繊維 プリント加工なし
B93: 5RGKB C DA8 | C93: ZIPPER
B95: 材質：樹脂 | C95: 43CM-5PCS. 45CM-5PCS.
C96: 43CM-3PCS. 45CM-3PCS.
C97: 45CMPCS.
B99: 3MGKB C DA8 | C99: ZIPPER
B100: 材質：樹脂 | C100: 16CM-10PCS. 17CM-10PCS.
C101: 16CM-6PCS. 17CM-6PCS.
C102: 17CM-8PCS.
B104: 132-723 | C104: TAPE
B105: 材質：綿 | C105: 15MM #010-6M #074-4M #050-3M
C106: 12MM #010-2M #074-2M #050-1M
C108: NF25SY-44
B109: PRV26 | C109: BUTTONS 11.5MM
B110: 材質：ユリア樹脂
C112: NF25SY-43
B113: 1000 | C113: COTTON 100% PIECE-DYED SLEEK
B114: 綾織 スレキ 先染め
B115: 短繊維 プリント加工なし
B117: 3MA-C GSN8 | C117: ZIPPER
C118: 15CM-4PCS. 16CM-4PCS.
C119: 15CM-8PCS. 16CM-9PCS.
