Workbook
Name pricetable: #REF!
Name pricetable: #REF!
Name pricetable: #REF!
Name pricetable: #REF!
Name pricetable: #REF!
Name pricetable: #REF!

Sheet shipper master
A1: 1 | B1: S/CODE | C1: SHIPPER NAME
A2: =A1+1 -> 2 | B2: SHIPPER | C2: SHUNYA CO., LTD.
A3: =A2+1 -> 3 | B3: SHIPPER ADDRESS 1 | C3: KENSHIN BLDG., 1F, 1-22-10 DOUGENZAKA,
A4: =A3+1 -> 4 | B4: SHIPPER ADDRESS 2 | C4: SHIBUYA-KU 150-0043
A5: =A4+1 -> 5 | B5: SHIPPER ADDRESS 3 | C5: TEL : +81(0)3-5459-1177
A6: =A5+1 -> 6 | B6: TEL
A7: =A6+1 -> 7 | B7: FAX
A8: =A7+1 -> 8 | B8: ATTN OR VAT NO.
A9: =A8+1 -> 9 | B9: BUYER | C9: VIVAN GARMENTS VIET NAM COMPANY LIMITED
A10: =A9+1 -> 10 | B10: BUYER ADDRESS1 | C10: D17 Street , Sai Gon South Residential Area
A11: =A10+1 -> 11 | B11: BUYER ADDRESS2 | C11: Hamlet 3 , Long Hau Commune , Can Giuoc District,
A12: =A11+1 -> 12 | B12: BUYER ADDRESS3 | C12: Long An Province , VietNam
A13: =A12+1 -> 13 | B13: TEL/FAX | C13: TEL : ( 084 ) 097 22 00 798 ATTN : MR. TUAN
A14: =A13+1 -> 14 | B14: ATTN
A15: =A14+1 -> 15 | B15: CONSIGNEE : | C15: - SAME AS BUYER -
A16: =A15+1 -> 16 | B16: CONSIGNEE ADDRESS1
A17: =A16+1 -> 17 | B17: CONSIGNEE ADDRESS2
A18: =A17+1 -> 18 | B18: CONSIGNEE ADDRESS3
A19: =A18+1 -> 19 | B19: TEL
A20: =A19+1 -> 20 | B20: FAX
A21: =A20+1 -> 21 | B21: ATTN | C21: NO COMMERCIAL
A22: =A21+1 -> 22 | B22: PAYMENT 1
A23: =A22+1 -> 23 | B23: PAYMENT 2
A24: =A23+1 -> 24 | B24: SHIPPER PER | C24: AIRCRAFT
A25: =A24+1 -> 25 | B25: INVOICE DATE | C25: MAY, 22 2026
A26: =A25+1 -> 26 | B26: INVOICE NO. | C26: SY-8100522VT-DD-01
A27: =A26+1 -> 27 | B27: CONTRACT NO. | C27: =C26 -> SY-8100522VT-DD-01
A28: =A27+1 -> 28 | B28: CONTRACT DATE
A29: =A28+1 -> 29 | B29: ORDER DATE
A30: =A29+1 -> 30 | B30: ORDER NO.
A31: =A30+1 -> 31 | B31: L/C DATE
A32: =A31+1 -> 32 | B32: FROM | C32: TOKYO, JAPAN
A33: =A32+1 -> 33 | B33: TO | C33: HOCHIMINH-CITY, VIETNAM
A34: =A33+1 -> 34 | B34: VIA
A35: =A34+1 -> 35 | B35: SHIPPING TERMS | C35: F.O.B. TOKYO IN YEN
A36: =A35+1 -> 36 | B36: TITTLE 1 | C36: FABRIC & PARTS FOR WEAR & SAMPLE CLOTHES
A37: =A36+1 -> 37 | B37: TITTLE 2
A38: =A37+1 -> 38 | B38: ATTACHE | C38: - DETAILS AS PER ATTACHED SHEET -
A39: =A38+1 -> 39 | B39: C/NO.
A40: =A39+1 -> 40 | B40: STYLE NO.
A41: =A40+1 -> 41 | B41: DESCRIPTION
A42: =A41+1 -> 42 | B42: Q'TY CODE
A43: =A42+1 -> 43 | B43: QUANTITY | C43: 1165.4M. 2952PCS.
A44: =A43+1 -> 44 | B44: UNIT PRICE
A45: =A44+1 -> 45 | B45: AMOUNT | C45: =invoice!O31 -> 1434293
A46: =A45+1 -> 46 | B46: DISCOUNT
A47: =A46+1 -> 47 | B47: DISCOUNT
A48: =A47+1 -> 48 | B48: SHIPPING TERMS | C48: F.O.B. TOKYO IN YEN
A49: =A48+1 -> 49 | B49: CASE MARK1 | C49: =C27 -> SY-8100522VT-DD-01
A50: =A49+1 -> 50 | B50: CASE MARK2 | C50: VIVAN GARMENTS VIET NAM COMPANY LIMITED
A51: =A50+1 -> 51 | B51: CASE MARK3 | C51: D17 Street , Sai Gon South Residential Area
A52: =A51+1 -> 52 | B52: CASE MARK4 | C52: Hamlet 3 , Long Hau Commune , Can Giuoc District,
A53: =A52+1 -> 53 | B53: CASE MARK5 | C53: Long An Province , VietNam
A54: =A53+1 -> 54 | B54: CASE MARK6 | C54: TEL : : ( 084 ) 097 22 00 798 ATTN : MR. TUAN
A55: =A54+1 -> 55 | B55: TOTAL | C55: 28PACKAGES
A56: =A55+1 -> 56 | B56: MANUFACTURED BY
A57: =A56+1 -> 57
A58: =A57+1 -> 58
A59: =A58+1 -> 59
A60: =A59+1 -> 60 | B60: ORIGIN | C60: COUNTRY OF ORIGIN : JAPAN,USA
A61: =A60+1 -> 61 | B61: OUR BANK
A62: =A61+1 -> 62
A63: =A62+1 -> 63 | B63: 持ち帰り条件 | C63: " THESE GOODS WILL BE RETURN TO JAPAN
A64: =A63+1 -> 64 | C64: AFTER MANUFACTURED AT VIET NAM "
A65: =A64+1 -> 65
A66: =A65+1 -> 66
A67: =A66+1 -> 67 | B67: ETD TYO
A68: =A67+1 -> 68 | B68: DELIVERY SCHEDULES | C68: END OF JUNE - BEG., OF MAR, 2018
A69: =A68+1 -> 69 | B69: INSURANCE | C69: COVERED BY SHIPPER
A70: =A69+1 -> 70 | B70: REMARK 1
A71: =A70+1 -> 71
A72: =A71+1 -> 72
A73: =A72+1 -> 73
A74: =A73+1 -> 74
A75: =A74+1 -> 75 | B75: AIR FREIGHT | C75: PREPAID
A76: =A75+1 -> 76 | B76: YOUR (OUR) FORWARDER
A77: =A76+1 -> 77
A78: =A77+1 -> 78 | B78: CUSTOMS AGENT | C78: MEITETSU WORLD TRANSPORT (MR. NAMIKI)
A79: =A78+1 -> 79 | B79: FORWARDER | C79: MEITETSU WORLD TRANSPORT (MR. NAMIKI)
A80: =A79+1 -> 80
A81: =A80+1 -> 81 | B81: C/O ISSUED DATE | C81: =C25 -> MAY, 22 2026
A82: =A81+1 -> 82
A83: =A82+1 -> 83 | B83: COUNTRY | C83: VIETNAM
A84: =A83+1 -> 84
A85: =A84+1 -> 85
A86: =A85+1 -> 86

Sheet case mark 
A2: ='shipper master'!C26 -> SY-8100522VT-DD-01 | I2: ='shipper master'!C26 -> SY-8100522VT-DD-01
A3: ='[2]shipper master'!C50 -> VIVAN GARMENTS VIET NAM | I3: ='[2]shipper master'!C50 -> VIVAN GARMENTS VIET NAM
A4: ='[2]shipper master'!C51 -> COMPANY LIMITED | I4: ='[2]shipper master'!C51 -> COMPANY LIMITED
A5: ='[2]shipper master'!C52 -> HOCHIMINH-CITY, VIETNAM | I5: ='[2]shipper master'!C52 -> HOCHIMINH-CITY, VIETNAM
A6: C/NO. | C6: 1 | I6: C/NO. | K6: 2
A7: ='[2]shipper master'!C54 -> MADE IN JAPAN | I7: ='[2]shipper master'!C54 -> MADE IN JAPAN
A13: ='shipper master'!C26 -> SY-8100522VT-DD-01 | I13: ='shipper master'!C26 -> SY-8100522VT-DD-01
A14: ='[2]shipper master'!C50 -> VIVAN GARMENTS VIET NAM | I14: ='[2]shipper master'!C50 -> VIVAN GARMENTS VIET NAM
A15: ='[2]shipper master'!C51 -> COMPANY LIMITED | I15: ='[2]shipper master'!C51 -> COMPANY LIMITED
A16: ='[2]shipper master'!C52 -> HOCHIMINH-CITY, VIETNAM | I16: ='[2]shipper master'!C52 -> HOCHIMINH-CITY, VIETNAM
A17: C/NO. | C17: 3 | I17: C/NO. | K17: 4
A18: ='[2]shipper master'!C54 -> MADE IN JAPAN | I18: ='[2]shipper master'!C54 -> MADE IN JAPAN

Sheet invoice
A1: INVOICE
A2: ='[1]shipper master'!C2 -> SHUNYA CO., LTD.
A3: ='[1]shipper master'!C3 -> KENSHIN BLDG., 1F, 1-22-10 DOUGENZAKA,
A4: ='[1]shipper master'!C4 -> SHIBUYA-KU 150-0043 | N4: ='[1]shipper master'!C6 -> 0
A5: ='[1]shipper master'!C5 -> TEL : +81(0)3-5459-1177 | N5: ='[1]shipper master'!C7 -> 0
A6: IMPORTER | F6: INVOICE NO. | N6: CASE MARK
A7: ='[1]shipper master'!C9 -> VIVAN GARMENTS VIET NAM COMPANY LIMITED | F7: ='shipper master'!C26 -> SY-8100522VT-DD-01
A8: ='[1]shipper master'!C10 -> D17 Street , Sai Gon South Residential Area | F8: INVOICE DATE | N8: ='shipper master'!C26 -> SY-8100522VT-DD-01
A9: ='[1]shipper master'!C11 -> Hamlet 3 , Long Hau Commune , Can Giuoc District, | F9: ='shipper master'!C25 -> MAY, 22 2026 | N9: VIVAN GARMENTS VIET NAM
A10: ='[1]shipper master'!C12 -> Long An Province , VietNam | F10: CONTRACT NO. | N10: COMPANY LIMITED
A11: ='[1]shipper master'!C13 -> TEL : ( 084 ) 097 22 00 798 ATTN : MR. TUAN | F11: ='shipper master'!C26 -> SY-8100522VT-DD-01 | N11: ='[2]shipper master'!C52 -> HOCHIMINH-CITY, VIETNAM
A12: CONSIGNEE | F12: ORDER NO. | N12: C/NO. 1-28
A13: ='[1]shipper master'!C15 -> - SAME AS BUYER - | F13: ='[1]shipper master'!C30 -> 0 | N13: MADE IN JAPAN
A14: ='[1]shipper master'!C16 -> 0 | F14: ORDER DATE
A15: ='[1]shipper master'!C17 -> 0 | F15: ='[1]shipper master'!C29 -> 0
A16: ='[1]shipper master'!C18 -> 0 | F16: L/C NO.
A17: ='[1]shipper master'!C19 -> 0
A18: PAYMENT METHOD
A19: ='[1]shipper master'!C21 -> NO COMMERCIAL
A20: SHIPPED PER | D20: FROM | F20: TO | N20: VIA
A21: ='[1]shipper master'!C24 -> AIRCRAFT | D21: ='[1]shipper master'!C32 -> TOKYO, JAPAN | G21: ='[1]shipper master'!C33 -> HOCHIMINH-CITY, VIETNAM
A22: C/NO. | B22: ART NO. | D22: DESCRIPTION OF GOODS | E22: COLOR | H22: SIZE | M22: Q'TY | N22: U/PRICE | O22: AMOUNT
B24: ='[1]shipper master'!C36 -> FABRIC & PARTS FOR WEAR & SAMPLE CLOTHES | N24: ='[1]shipper master'!C48 -> F.O.B. TOKYO IN YEN
B26: ='[1]shipper master'!C37 -> 0 | M26: =SUM(NARITA!E135,NARITA2!E42) -> 1165.4 | N26: M. | O26: =SUM(NARITA!H135,NARITA2!H42) -> 1246857
M27: =SUM(NARITA!E136,NARITA2!E43) -> 2952 | N27: PCS. | O27: =SUM(NARITA!H136,NARITA2!H43) -> 187436
M28: =NARITA!E137 -> 0 | O28: =NARITA!H137 -> 0
B29: ='[1]shipper master'!C38 -> - DETAILS AS PER ATTACHED SHEET -
B31: TOTAL : | E31: =M26 -> 1165.4 | J31: M. | K31: =K29 -> 0 | L31: =M27 -> 2952 | M31: PCS. | O31: =SUM(O26:O30) -> 1434293
A34: ='[1]shipper master'!C63 -> " THESE GOODS WILL BE RETURN TO JAPAN | I34: " NO COMMER VALUE | M34: " NO COMMERCIAL VALUE
A35: ='[1]shipper master'!C64 -> AFTER MANUFACTURED AT VIET NAM " | I35: VALUE FOR CUSTOMS PURPOSE ONLY " | M35: VALUE FOR CUSTOMS PURPOSE ONLY "
D36: ='[1]shipper master'!C58 -> 0
A37: ='[1]shipper master'!C60 -> COUNTRY OF ORIGIN : JAPAN
A39: TOTAL CARTONS : | D39: 28CARTONS
A40: TOTAL GROSS WEIGHT : | D40: KGS

Sheet NARITA
A2: - ATTACHED SHEET -
A4: C/NO. | B4: ART NO. | C4: COLOR | D4: DESCRIPTION OF GOODS | E4: Q'TY | F4: U/PRICE | H4: AMOUNT | I4: 佐川伝票・明細 | J4: 搬入日 | K4: 伝票NO | L4: 搬入内容 | M4: 数量 | N4: 箱数
B6: (H.S. CODE) | D6: =[3]invoice!B24 -> FABRIC & PARTS FOR WEAR & SAMPLE CLOTHES | G6: ='[2]shipper master'!C48 -> F.O.B. TOKYO IN YEN
D7: MADE IN JAPAN
A8: 1-2 | D8: STYLE:22SY-65 | N8: 2
B9: SB2050 | C9: C/#5 BLACK | D9: WOVEN FABRIC | E9: 54.5 | F9: M. | G9: 950 | H9: =E9*G9 -> 51775 | I9: 入庫NO.220800831 | J9: 5/7
B10: WOVEN FABRIC | D10: COTTON 95% PU5% | E10: 53.5 | F10: M. | G10: 950 | H10: =E10*G10 -> 50825
B11: 綾織 ツイル 後染め | D11: WIDTH:123CM (286ｇ/㎡ )
B12: 短繊維 プリント加工なし
A14: 3-4 | D14: STYLE:25SY-44 | N14: 2
B15: 02100097248 | C15: C/#099 BLACK | D15: WOVEN FABRIC | E15: 51 | F15: M. | G15: 1380 | H15: =E15*G15 -> 70380 | I15: 入庫NO.22080907 | J15: 5/13
B16: WOVEN FABRIC | C16: C/#550 KHAKI | D16: LYOCELL 59% / POLYESTER 39% / POLYURETHANE 2% | E16: 50 | F16: M. | G16: 1380 | H16: =E16*G16 -> 69000
B17: 綾織 ツイル 後染め | D17: WIDTH:132CM (162ｇ/㎡ )
B18: 短繊維、プリント加工なし
A20: 5-6 | D20: STYLE:22SY-53 | N20: 2
B21: M6543FT | C21: C/#002 BLACK | D21: WOVEN FABRIC | E21: 92 | F21: M. | G21: 1060 | H21: =E21*G21 -> 97520 | I21: 入庫NO.22080833 | J21: 5/9
B22: WOVEN FABRIC | D22: NYLON 100%
B23: 綾織 ツイル 後染め | D23: WIDTH:115CM (360ｇ/㎡ )
B24: 長繊維、プリント加工なし
A26: 7-8 | D26: STYLE:22SY-66 | N26: 2
B27: CS231B | C27: C/#B-BO BLACK | D27: WOVEN FABRIC | E27: 30 | F27: M. | G27: 1670 | H27: =E27*G27 -> 50100 | I27: 入庫NO.22080853 | J27: 5/11
B28: WOVEN FABRIC | C28: C/#B-BO BLACK | D28: COTTON 95% PU5% | E28: 50 | F28: M. | G28: 1670 | H28: =E28*G28 -> 83500 | I28: 入庫NO.22080854 | J28: 5/11
B29: 綾織 デニム 先染め | D29: WIDTH:125CM (250ｇ/㎡ )
B30: 短繊維、プリント加工なし
A32: 9-10 | D32: STYLE:25SY-45 | N32: 2
B33: YG12006 | C33: C/#SP ECRU | D33: KNIT FABRIC | E33: 29.7 | F33: M. | G33: 1040 | H33: =E33*G33 -> 30888 | I33: 入庫NO.22080937 | J33: 5/13
B34: KNIT FABRIC | C34: C/#10 BLACK | D34: COTTON100% | E34: 27.8 | F34: M. | G34: 1040 | H34: =E34*G34 -> 28912
B35: 丸編み ワッフル編み 綿染め | D35: WIDTH:150CM (412ｇ/㎡ )
B36: 短繊維、プリント加工なし
A38: 11-12 | D38: STYLE:26SY-08(26A-SH-02) / 26A-AC04 | N38: 2
B39: D5005 | C39: C/#NAVY | D39: WOVEN FABRIC | E39: 214.3 | F39: M. | G39: 1200 | H39: =E39*G39 -> 257160 | I39: 入庫NO.22080996 | J39: 5/16
B40: WOVEN FABRIC | D40: COTTON100%
B41: 平織 ブロード 後染め | D41: WIDTH:112CM (107ｇ/㎡ )
B42: 短繊維、プリント加工あり
A44: 13-15 | D44: STYLE:25SY-55(cc26aw-46) | N44: 2
B45: H-1121 | C45: C/#52 GRAY | D45: KNIT FABRIC | E45: 9.4 | F45: M. | G45: 2530 | H45: =E45*G45 -> 23782 | I45: 入庫NO.22081042 | J45: 5/19
B46: KNIT FABRIC | C46: C/#14 BLACK | D46: PILE：ACRYLIC 100% / GROUND：POLYESTER 100% | E46: 7 | F46: M. | G46: 2530 | H46: =E46*G46 -> 17710
B47: 丸編み ループパイル編 先染め | C47: C/#402 BEIGE | D47: WIDTH:140CM (110ｇ/㎡ ) | E47: 18 | F47: M. | G47: 2530 | H47: =E47*G47 -> 45540
B48: 長繊維、プリント加工なし
A50: 16 | D50: STYLE:22SY-65 | N50: 1
B51: 9900 | C51: C/#258 ECRU | D51: WOVEN FABRIC | E51: 8 | F51: M. | G51: 580 | H51: =E51*G51 -> 4640 | I51: 入庫NO.22081080 | J51: 5/20
B52: WOVEN FABRIC | D52: COTTON 100%
B53: 綾織 ツイル 先染め | D53: WIDTH:120CM (286ｇ/㎡ )
B54: 短繊維 プリント加工なし
A56: 17 | D56: STYLE:25SY-51(26A-JK01) | N56: 1
B57: RMD-3401 | C57: C/#06 BROWN | D57: WOVEN FABRIC | E57: 57.5 | F57: M. | G57: 1030 | H57: =E57*G57 -> 59225 | I57: 入庫NO.22081148
B58: WOVEN FABRIC | D58: COTTON 100%
B59: 綾織 ツイル 先染め | D59: WIDTH:112CM (198ｇ/㎡ )
B60: 短繊維 プリント加工なし
A62: 18-19 | D62: STYLE:26SY-06(26A-JK04) | N62: 2
B63: SB42221-BD | C63: C/#BLACK | D63: WOVEN FABRIC | E63: 51.2 | F63: M. | G63: 1200 | H63: =E63*G63 -> 61440 | I63: 入庫NO.22081129
B64: WOVEN FABRIC | D64: COTTON 100%
B65: ボンディング生地 別珍×ブロード 平織 | D65: WIDTH:150CM (273ｇ/㎡ )
B66: 短繊維 プリント加工なし 後染め
A68: 20-21 | D68: STYLE:25SY-43 | N68: 2
B69: SBW201-VZ | C69: C/#BK | D69: WOVEN FABRIC | E69: 52.5 | F69: M. | G69: 1200 | H69: =E69*G69 -> 63000 | I69: 岡山県貨物運送
B70: WOVEN FABRIC | C70: c/#IV | D70: POLYESTER65% COTTON35% | E70: 50.5 | F70: M. | G70: 1200 | H70: =E70*G70 -> 60600 | I70: 4046120422
B71: 朱子織 サテン | D71: WIDTH:145CM (382ｇ/㎡ )
B72: 短繊維 プリント加工なし 後染め
A74: 22-23 | D74: STYLE:25SY-13(AVANI-01) | N74: 2
B75: 117 | C75: c/#102 | D75: KNIT FABRIC | E75: 1 | F75: M. | G75: 530 | H75: =E75*G75 -> 530
B76: KNIT FABRIC | C76: c/#403 | D76: COTTON100% | E76: 1 | F76: M. | G76: 530 | H76: =E76*G76 -> 530
B77: 天竺 先染め | C77: c/#412 | D77: WIDTH:170CM (141.1ｇ/㎡ ) | E77: 1 | F77: M. | G77: 530 | H77: =E77*G77 -> 530
B78: 短繊維、プリント加工なし
D80: STYLE:25SY-13(AVANI-01)
B81: 493 | C81: c/#58 | D81: KNIT FABRIC | E81: 1 | F81: M. | G81: 750 | H81: =E81*G81 -> 750
B82: KNIT FABRIC | C82: c/#120 | D82: COTTON100% | E82: 1 | F82: M. | G82: 750 | H82: =E82*G82 -> 750
B83: フライス 先染め | C83: c/#131 | D83: WIDTH:48CM (243ｇ/㎡ ) | E83: 1 | F83: M. | G83: 750 | H83: =E83*G83 -> 750
B84: 短繊維、プリント加工なし | C84: c/#330 | E84: 1 | F84: M. | G84: 750 | H84: =E84*G84 -> 750
I85: 入庫NO.22081130
D87: STYLE:26A-SH01(26SY-07)
B88: ARMY4 | C88: c/#PINK | D88: button 11.5mm | E88: 340 | F88: PCS. | G88: 50 | H88: =E88*G88 -> 17000
B89: button | C89: c/#BLUE | E89: 340 | F89: PCS. | G89: 50 | H89: =E89*G89 -> 17000
B90: 材質：ユリア樹脂
D93: STYLE:25SY-43
B94: BQ PLAIN | C94: c/#SNR SILVER | D94: tuck button 16.8mm | E94: 30 | F94: PCS. | G94: 30 | H94: =E94*G94 -> 900
B95: Tack button
B96: 素材：真鍮
D98: STYLE:26A-JK02,26A-JK01,26A-PT03,26A-PT04
B99: PRESTIGE WOVEN piece name | D99: PRESTIGE WOVEN piece name | E99: 300 | F99: PCS. | G99: 30 | H99: =E99*G99 -> 9000
B100: PRESTIGE paper name | D100: PRESTIGE paper name | E100: 210 | F100: PCS. | G100: 80 | H100: =E100*G100 -> 16800
D101: STYLE:cc26aw-46
B102: 77circa WOVEN name | D102: 77circa WOVEN name | E102: 20 | F102: PCS. | G102: 30 | H102: =E102*G102 -> 600
D103: STYLE:25SY-45,25SY-43,25SY-44
B104: no effect WOVEN name | D104: no effect WOVEN name | E104: 120 | F104: PCS. | G104: 30 | H104: =E104*G104 -> 3600
B105: no effect WOVEN piece name | D105: no effect WOVEN piece name | E105: 120 | F105: PCS. | G105: 20 | H105: =E105*G105 -> 2400
D106: STYLE:22SY-53,22SY-65,22SY-66
B107: EnGage WOVEN name | D107: EnGage WOVEN name | E107: 110 | F107: PCS. | G107: 30 | H107: =E107*G107 -> 3300
B108: EnGage WOVEN piece name | D108: EnGage WOVEN piece name | E108: 100 | F108: PCS. | G108: 20 | H108: =E108*G108 -> 2000
D109: STYLE:25SY-15(23sy-04),25SY-47(23sy-05)
B110: WOVEN quality name | D110: WOVEN quality name | E110: 40 | F110: PCS. | G110: 40 | H110: =E110*G110 -> 1600
B112: 22SY-53 sample | D112: men's coach jacket SAMPLE CLOTHES | E112: 1 | F112: PCS. | G112: 2000 | H112: =E112*G112 -> 2000
B113: 22SY-65 sample | D113: men's twill pants SAMPLE CLOTHES | E113: 1 | F113: PCS. | G113: 2000 | H113: =E113*G113 -> 2000
B114: 22SY-66 sample | D114: men's denim shirt SAMPLE CLOTHES | E114: 1 | F114: PCS. | G114: 2000 | H114: =E114*G114 -> 2000
B115: 25SY-43 sample | D115: men's pants SAMPLE CLOTHES | E115: 2 | F115: PCS. | G115: 2000 | H115: =E115*G115 -> 4000
B116: 25SY-44 sample | D116: men's shirt SAMPLE CLOTHES | E116: 2 | F116: PCS. | G116: 2000 | H116: =E116*G116 -> 4000
B117: 25SY-45 sample | D117: men's knit tanktop SAMPLE CLOTHES | E117: 2 | F117: PCS. | G117: 2000 | H117: =E117*G117 -> 4000
B118: 26A-JK01 sample | D118: men's corduroy jacket SAMPLE CLOTHES | E118: 1 | F118: PCS. | G118: 2000 | H118: =E118*G118 -> 2000
B119: 26A-JK02 sample | D119: men's denim jacket SAMPLE CLOTHES | E119: 1 | F119: PCS. | G119: 2000 | H119: =E119*G119 -> 2000
B120: 26A-JK03sample | D120: men's jersey jacket SAMPLE CLOTHES | E120: 1 | F120: PCS. | G120: 2000 | H120: =E120*G120 -> 2000
...

Sheet NARITA2
A2: - ATTACHED SHEET -
A4: C/NO. | B4: ART NO. | C4: COLOR | D4: DESCRIPTION OF GOODS | E4: Q'TY | F4: U/PRICE | H4: AMOUNT | I4: 佐川伝票・明細 | J4: 搬入日 | K4: 伝票NO | L4: 搬入内容 | M4: 数量 | N4: 箱数
B6: (H.S. CODE) | D6: FABRIC & PARTS FOR WEAR | G6: ='[4]shipper master'!C48 -> F.O.B. TOKYO IN YEN
D7: MADE IN JAPAN
A9: 25-26 | D9: 25SY-49/25SY-57 | I9: 入庫NO.22080800 | J9: 5/1 | N9: 2
B10: B210 | C10: BK | D10: WAIST ELASTIC 60mm | E10: 150 | F10: M. | G10: 190 | H10: =SUM(E10*G10) -> 28500
B11: 材質：ポリエステル
B12: 3CF C DA | D12: metal ZIPPER 16CM | E12: 288 | F12: PCS. | G12: 40 | H12: =SUM(E12*G12) -> 11520
B13: 材質：メタル | D13: #058-96PCS / #580-96PCS / #570-96PCS
D15: 25SY-49/56/57/48
B16: 1000 | D16: COTTON 100% PIECE-DYED SLEEK
B17: 綾織 スレキ 先染め | D17: #73-7M / #1-1-7M / #189-7M / #258-29M | E17: 50 | F17: M. | G17: 540 | H17: =SUM(E17*G17) -> 27000
D19: 25SY-56
B20: 3YGRDS C GSN8 | C20: 560 | D20: ZIPPER | E20: 35 | F20: PCS. | G20: 80 | H20: =SUM(E20*G20) -> 2800
B21: 材質：メタル | C21: A | D21: 16.5CM-17 / 17.5CM-18
D23: 25SY-57
B24: 3CF C DA | D24: ZIPPER 16CM
B25: 材質：樹脂 | D25: #570-96PCS / #580-96PCS / #058-96PCS | E25: 288 | F25: PCS. | G25: 40 | H25: =SUM(E25*G25) -> 11520
D27: 25SY-56
B28: 3YGRDS C GSN8 | D28: ZIPPER
B29: 材質：樹脂 | D29: #560 16.5CM-17PCS / 17.5CM-18PCS | E29: 35 | F29: PCS. | G29: 80 | H29: =SUM(E29*G29) -> 2800
D30: #580 16.5CM-17PCS / 17.5CM-18PCS | E30: 35 | F30: PCS. | G30: 80 | H30: =SUM(E30*G30) -> 2800
D32: 25SY-56
B33: 3CF C DA | D33: ZIPPER 17CM
B34: 材質：樹脂 | D34: #580-48PCS / #058-48PCS / #570-48PCS | E34: 144 | F34: PCS. | G34: 42 | H34: =SUM(E34*G34) -> 6048
A36: 27 | D36: 25SY-48 | I36: 入庫NO.22081043 | J36: 5/19 | N36: 1
B37: 5CIF M DA86 | D37: ZIPPER
B38: 材質：樹脂 | D38: 74CM #580-6 #058-6 #570-6 | E38: 18 | F38: PCS. | G38: 200 | H38: =E38*G38 -> 3600
D39: 75.5CM #580-10 #058-10 #570-10 | E39: 30 | F39: PCS. | G39: 206 | H39: =E39*G39 -> 6180
D40: 77CM #580-8 #058-8 #570-8 | E40: 24 | F40: PCS. | G40: 207 | H40: =E40*G40 -> 4968
B42: TOTAL : | C42: 3 CTNS | E42: =SUMIF($F$8:$F$40,"M.",$E$8:$E$40) -> 200 | F42: M. | H42: =SUMIF($F$8:$F$40,"M.",$H$8:$H$40) -> 55500
E43: =SUMIF($F$8:$F$40,"PCS.",$E$8:$E$40) -> 897 | F43: PCS. | H43: =SUMIF($F$8:$F$40,"PCS.",$H$8:$H$40) -> 52236
E44: - | F44: SET. | H44: =SUMIF($F$9:$F$35,"SET.",$H$9:$H$35) -> 0
G45: TOTAL | H45: =SUM(H42:H44) -> 107736

Sheet サンプル製品カタログ
D1: ITEM
B2: NAME | C2: color | E2: lady's or men's | F2: WOVEN or KNIT | G2: picture | H2: Composition | I2: packingNo.
B3: men's coach jacket SAMPLE CLOTHES | C3: BEIGE | D3: 22SY-53 sample | E3: men's | F3: WOVEN | H3: NYLON 100% | I3: 22-23
B4: men's twill pants SAMPLE CLOTHES | C4: BLACK | D4: 22SY-65 sample | E4: men's | F4: WOVEN | H4: COTTON 95% PU5%
B5: men's denim shirt SAMPLE CLOTHES | C5: BLUE | D5: 22SY-66 sample | E5: men's | F5: WOVEN | H5: COTTON 95% PU5%
B6: men's pants SAMPLE CLOTHES | C6: BLACK BEIGE | D6: 25SY-43 sample | E6: men's | F6: WOVEN | H6: POLYESTER65% COTTON35%
B7: men's shirt SAMPLE CLOTHES | C7: BLACK KHAKI | D7: 25SY-44 sample | E7: men's | F7: WOVEN | H7: LYOCELL 59% / POLYESTER 39% / POLYURETHANE 2%
B8: men's knit tanktop SAMPLE CLOTHES | C8: BLACK BEIGE | D8: 25SY-45 sample | E8: men's | F8: WOVEN | H8: COTTON 100%
B9: men's corduroy jacket SAMPLE CLOTHES | C9: BROWN | D9: 26A-JK01 sample | E9: men's | F9: WOVEN | H9: COTTON 100%
B10: men's denim jacket SAMPLE CLOTHES | C10: BLUE | D10: 26A-JK02 sample | E10: men's | F10: WOVEN | H10: COTTON 100%
B11: men's jersey jacket SAMPLE CLOTHES | C11: NAVY | D11: 26A-JK03sample | E11: men's | F11: WOVEN | H11: POLYESTER 100%
B12: men's denim pants SAMPLE CLOTHES | C12: BLUE | D12: 26A-PT03 sample | E12: men's | F12: WOVEN | H12: COTTON 100%
B13: men's denim pants SAMPLE CLOTHES | C13: BLACK | D13: 26A-PT04 sample | E13: men's | F13: WOVEN | H13: COTTON 100%
B14: men's boa jacket SAMPLE CLOTHES | C14: BEIGE | D14: cc26aw-46 sample | E14: men's | F14: WOVEN | H14: PILE：ACRYLIC 100% / GROUND：POLYESTER 100%

Sheet LABEL
A2: LABEL SHEET -
A4: C/NO. | B4: ART NO. | C4: DESCRIPTION OF GOODS | D4: 原産国
A5: 1-2 | C5: STYLE:22SY-65
B6: SB2050 | C6: WOVEN FABRIC | D6: MADE IN JAPAN
B7: WOVEN FABRIC | C7: COTTON 95% PU5% | D7: SHUNYA CO., LTD.
B8: 綾織 ツイル 後染め | C8: WIDTH:123CM (286ｇ/㎡ )
B9: 短繊維 プリント加工なし
A11: C/NO. | B11: ART NO. | C11: DESCRIPTION OF GOODS | D11: 原産国
A12: 3-4 | C12: STYLE:25SY-44
B13: 02100097248 | C13: WOVEN FABRIC | D13: MADE IN JAPAN
B14: WOVEN FABRIC | C14: LYOCELL 59% / POLYESTER 39% / POLYURETHANE 2% | D14: SHUNYA CO., LTD.
B15: 綾織 ツイル 後染め | C15: WIDTH:132CM (162ｇ/㎡ )
B16: 短繊維、プリント加工なし
A18: C/NO. | B18: ART NO. | C18: DESCRIPTION OF GOODS | D18: 原産国
A19: 5-6 | C19: STYLE:22SY-53
B20: M6543FT | C20: WOVEN FABRIC | D20: MADE IN JAPAN
B21: WOVEN FABRIC | C21: NYLON 100% | D21: SHUNYA CO., LTD.
B22: 綾織 ツイル 後染め | C22: WIDTH:115CM (360ｇ/㎡ )
B23: 長繊維、プリント加工なし
A25: C/NO. | B25: ART NO. | C25: DESCRIPTION OF GOODS | D25: 原産国
A26: 7-8 | C26: STYLE:22SY-66
B27: CS231B | C27: WOVEN FABRIC | D27: MADE IN JAPAN
B28: WOVEN FABRIC | C28: COTTON 95% PU5% | D28: SHUNYA CO., LTD.
B29: 綾織 デニム 先染め | C29: WIDTH:125CM (250ｇ/㎡ )
B30: 短繊維、プリント加工なし
A32: C/NO. | B32: ART NO. | C32: DESCRIPTION OF GOODS | D32: 原産国
A33: 9-10 | C33: STYLE:25SY-45
B34: YG12006 | C34: KNIT FABRIC | D34: MADE IN JAPAN
B35: KNIT FABRIC | C35: COTTON100% | D35: SHUNYA CO., LTD.
B36: 丸編み ワッフル編み 綿染め | C36: WIDTH:150CM (412ｇ/㎡ )
B37: 短繊維、プリント加工なし
A39: C/NO. | B39: ART NO. | C39: DESCRIPTION OF GOODS | D39: 原産国
A40: 11-12 | C40: STYLE:26SY-08(26A-SH-02) / 26A-AC04
B41: D5005 | C41: WOVEN FABRIC | D41: MADE IN JAPAN
B42: WOVEN FABRIC | C42: COTTON100% | D42: SHUNYA CO., LTD.
B43: 平織 ブロード 後染め | C43: WIDTH:112CM (107ｇ/㎡ )
B44: 短繊維、プリント加工あり
A46: C/NO. | B46: ART NO. | C46: DESCRIPTION OF GOODS | D46: 原産国
A47: 13-15 | C47: STYLE:25SY-55(cc26aw-46)
B48: H-1121 | C48: KNIT FABRIC | D48: MADE IN JAPAN
B49: KNIT FABRIC | C49: PILE：ACRYLIC 100% / GROUND：POLYESTER 100% | D49: SHUNYA CO., LTD.
B50: 丸編み ループパイル編 先染め | C50: WIDTH:140CM (110ｇ/㎡ )
B51: 長繊維、プリント加工なし
A53: C/NO. | B53: ART NO. | C53: DESCRIPTION OF GOODS | D53: 原産国
A54: 16 | C54: STYLE:22SY-65
B55: 9900 | C55: WOVEN FABRIC | D55: MADE IN JAPAN
B56: WOVEN FABRIC | C56: COTTON 100% | D56: SHUNYA CO., LTD.
B57: 綾織 ツイル 先染め | C57: WIDTH:120CM (286ｇ/㎡ )
B58: 短繊維 プリント加工なし
A60: C/NO. | B60: ART NO. | C60: DESCRIPTION OF GOODS | D60: 原産国
A61: 17 | C61: STYLE:25SY-51(26A-JK01)
B62: RMD-3401 | C62: WOVEN FABRIC | D62: MADE IN JAPAN
B63: WOVEN FABRIC | C63: COTTON 100% | D63: SHUNYA CO., LTD.
B64: 綾織 ツイル 先染め | C64: WIDTH:112CM (198ｇ/㎡ )
B65: 短繊維 プリント加工なし
A67: C/NO. | B67: ART NO. | C67: DESCRIPTION OF GOODS | D67: 原産国
A68: 18-19 | C68: STYLE:26SY-06(26A-JK04)
B69: SB42221-BD | C69: WOVEN FABRIC | D69: MADE IN JAPAN
B70: WOVEN FABRIC | C70: COTTON 100% | D70: SHUNYA CO., LTD.
B71: ボンディング生地 別珍×ブロード 平織 | C71: WIDTH:150CM (273ｇ/㎡ )
B72: 短繊維 プリント加工なし 後染め
A74: C/NO. | B74: ART NO. | C74: DESCRIPTION OF GOODS | D74: 原産国
A75: 20-21 | C75: STYLE:25SY-43
B76: SBW201-VZ | C76: WOVEN FABRIC | D76: MADE IN JAPAN
B77: WOVEN FABRIC | C77: POLYESTER65% COTTON35% | D77: SHUNYA CO., LTD.
B78: 朱子織 サテン | C78: WIDTH:145CM (382ｇ/㎡ )
B79: 短繊維 プリント加工なし 後染め
A81: C/NO. | B81: ART NO. | C81: DESCRIPTION OF GOODS | D81: 原産国
A82: 22-23 | C82: STYLE:25SY-13(AVANI-01)
B83: 117 | C83: KNIT FABRIC
B84: KNIT FABRIC | C84: COTTON100%
B85: 天竺 先染め | C85: WIDTH:170CM (141.1ｇ/㎡ )
B86: 短繊維、プリント加工なし
C88: STYLE:25SY-13(AVANI-01)
B89: 493 | C89: KNIT FABRIC
B90: KNIT FABRIC | C90: COTTON100%
B91: フライス 先染め | C91: WIDTH:48CM (243ｇ/㎡ )
B92: 短繊維、プリント加工なし
C95: STYLE:26A-SH01(26SY-07)
B96: ARMY4 | C96: button 11.5mm
B97: button
B98: 材質：ユリア樹脂
D100: MADE IN JAPAN
C101: STYLE:25SY-43 | D101: SHUNYA CO., LTD.
B102: BQ PLAIN | C102: tuck button 16.8mm
B103: Tack button
B104: 素材：真鍮
C106: STYLE:26A-JK02,26A-JK01,26A-PT03,26A-PT04
B107: PRESTIGE WOVEN piece name | C107: PRESTIGE WOVEN piece name
B108: PRESTIGE paper name | C108: PRESTIGE paper name
C109: STYLE:cc26aw-46
B110: 77circa WOVEN name | C110: 77circa WOVEN name
C111: STYLE:25SY-45,25SY-43,25SY-44
B112: no effect WOVEN name | C112: no effect WOVEN name
B113: no effect WOVEN piece name | C113: no effect WOVEN piece name
C114: STYLE:22SY-53,22SY-65,22SY-66
B115: EnGage WOVEN name | C115: EnGage WOVEN name
B116: EnGage WOVEN piece name | C116: EnGage WOVEN piece name
C117: STYLE:25SY-15(23sy-04),25SY-47(23sy-05)
B118: WOVEN quality name | C118: WOVEN quality name
...
